{
  "model": "PROCESSED_A_GFPN_s42",
  "model_path": "/home/orangepi/Paper_pass_Projects/yolov8_rknn-toolkit2-lite/0422_RKNN_model/PROCESSED_A_GFPN_s42_640_fp.rknn",
  "class_names": [
    "Rust",
    "Cracks",
    "patches",
    "Scratches",
    "Pitting"
  ],
  "image_count": 350,
  "predictions": [
    {
      "image_name": "test_1.jpg",
      "class_id": 2,
      "class_name": "patches",
      "conf": 0.8942365646362305,
      "x1": 379.25970458984375,
      "y1": 403.1431884765625,
      "x2": 637.044677734375,
      "y2": 475.4108581542969
    },
    {
      "image_name": "test_10.jpg",
      "class_id": 2,
      "class_name": "patches",
      "conf": 0.9053223133087158,
      "x1": 362.90716552734375,
      "y1": 147.84898376464844,
      "x2": 474.44097900390625,
      "y2": 311.01495361328125
    },
    {
      "image_name": "test_10.jpg",
      "class_id": 2,
      "class_name": "patches",
      "conf": 0.9020932912826538,
      "x1": 556.6755981445312,
      "y1": 248.13540649414062,
      "x2": 639.0,
      "y2": 534.7079467773438
    },
    {
      "image_name": "test_10.jpg",
      "class_id": 2,
      "class_name": "patches",
      "conf": 0.8746137022972107,
      "x1": 368.58209228515625,
      "y1": 0.0,
      "x2": 530.9444580078125,
      "y2": 97.62442779541016
    },
    {
      "image_name": "test_101.jpg",
      "class_id": 0,
      "class_name": "Rust",
      "conf": 0.8143482804298401,
      "x1": 287.51007080078125,
      "y1": 140.16497802734375,
      "x2": 386.586669921875,
      "y2": 435.8152770996094
    },
    {
      "image_name": "test_102.jpg",
      "class_id": 4,
      "class_name": "Pitting",
      "conf": 0.7689067125320435,
      "x1": 277.0440368652344,
      "y1": 259.324951171875,
      "x2": 367.2325439453125,
      "y2": 420.98101806640625
    },
    {
      "image_name": "test_106.jpg",
      "class_id": 0,
      "class_name": "Rust",
      "conf": 0.4052722156047821,
      "x1": 280.0650634765625,
      "y1": 128.70761108398438,
      "x2": 378.59246826171875,
      "y2": 425.82244873046875
    },
    {
      "image_name": "test_11.jpg",
      "class_id": 2,
      "class_name": "patches",
      "conf": 0.9053223133087158,
      "x1": 362.90716552734375,
      "y1": 147.84898376464844,
      "x2": 474.44097900390625,
      "y2": 311.01495361328125
    },
    {
      "image_name": "test_11.jpg",
      "class_id": 2,
      "class_name": "patches",
      "conf": 0.9020932912826538,
      "x1": 556.6755981445312,
      "y1": 248.13540649414062,
      "x2": 639.0,
      "y2": 534.7079467773438
    },
    {
      "image_name": "test_11.jpg",
      "class_id": 2,
      "class_name": "patches",
      "conf": 0.8746137022972107,
      "x1": 368.58209228515625,
      "y1": 0.0,
      "x2": 530.9444580078125,
      "y2": 97.62442779541016
    },
    {
      "image_name": "test_111.jpg",
      "class_id": 1,
      "class_name": "Cracks",
      "conf": 0.8223318457603455,
      "x1": 519.0615234375,
      "y1": 44.133758544921875,
      "x2": 571.3192138671875,
      "y2": 271.2016906738281
    },
    {
      "image_name": "test_112.jpg",
      "class_id": 1,
      "class_name": "Cracks",
      "conf": 0.8472108244895935,
      "x1": 521.617919921875,
      "y1": 524.6608276367188,
      "x2": 571.961669921875,
      "y2": 639.0
    },
    {
      "image_name": "test_113.jpg",
      "class_id": 1,
      "class_name": "Cracks",
      "conf": 0.8187368512153625,
      "x1": 199.21881103515625,
      "y1": 45.35418701171875,
      "x2": 251.01698303222656,
      "y2": 270.4235534667969
    },
    {
      "image_name": "test_114.jpg",
      "class_id": 1,
      "class_name": "Cracks",
      "conf": 0.8474634885787964,
      "x1": 200.5608367919922,
      "y1": 525.3145141601562,
      "x2": 252.1340789794922,
      "y2": 639.0
    },
    {
      "image_name": "test_115.jpg",
      "class_id": 0,
      "class_name": "Rust",
      "conf": 0.5684158205986023,
      "x1": 271.50714111328125,
      "y1": 11.291557312011719,
      "x2": 405.61383056640625,
      "y2": 235.195068359375
    },
    {
      "image_name": "test_116.jpg",
      "class_id": 0,
      "class_name": "Rust",
      "conf": 0.44836586713790894,
      "x1": 258.3763427734375,
      "y1": 196.71661376953125,
      "x2": 378.65594482421875,
      "y2": 394.3774108886719
    },
    {
      "image_name": "test_12.jpg",
      "class_id": 2,
      "class_name": "patches",
      "conf": 0.8588370084762573,
      "x1": 0.0,
      "y1": 407.2228698730469,
      "x2": 163.18637084960938,
      "y2": 476.27008056640625
    },
    {
      "image_name": "test_12.jpg",
      "class_id": 0,
      "class_name": "Rust",
      "conf": 0.44785264134407043,
      "x1": 211.2421112060547,
      "y1": 12.881377220153809,
      "x2": 261.2470703125,
      "y2": 39.11396789550781
    },
    {
      "image_name": "test_120.jpg",
      "class_id": 0,
      "class_name": "Rust",
      "conf": 0.4014531373977661,
      "x1": 257.693603515625,
      "y1": 206.7048797607422,
      "x2": 378.74920654296875,
      "y2": 396.4340515136719
    },
    {
      "image_name": "test_123.jpg",
      "class_id": 0,
      "class_name": "Rust",
      "conf": 0.5684158205986023,
      "x1": 271.50714111328125,
      "y1": 11.291557312011719,
      "x2": 405.61383056640625,
      "y2": 235.195068359375
    },
    {
      "image_name": "test_124.jpg",
      "class_id": 0,
      "class_name": "Rust",
      "conf": 0.44836586713790894,
      "x1": 258.3763427734375,
      "y1": 196.71661376953125,
      "x2": 378.65594482421875,
      "y2": 394.3774108886719
    },
    {
      "image_name": "test_126.jpg",
      "class_id": 0,
      "class_name": "Rust",
      "conf": 0.4014531373977661,
      "x1": 257.693603515625,
      "y1": 206.7048797607422,
      "x2": 378.74920654296875,
      "y2": 396.4340515136719
    },
    {
      "image_name": "test_127.jpg",
      "class_id": 1,
      "class_name": "Cracks",
      "conf": 0.9058233499526978,
      "x1": 270.57110595703125,
      "y1": 271.1865234375,
      "x2": 401.6007080078125,
      "y2": 381.4038391113281
    },
    {
      "image_name": "test_128.jpg",
      "class_id": 1,
      "class_name": "Cracks",
      "conf": 0.8660192489624023,
      "x1": 269.6099548339844,
      "y1": 264.29632568359375,
      "x2": 404.2156677246094,
      "y2": 374.05615234375
    },
    {
      "image_name": "test_129.jpg",
      "class_id": 1,
      "class_name": "Cracks",
      "conf": 0.9058233499526978,
      "x1": 270.57110595703125,
      "y1": 271.1865234375,
      "x2": 401.6007080078125,
      "y2": 381.4038391113281
    },
    {
      "image_name": "test_13.jpg",
      "class_id": 1,
      "class_name": "Cracks",
      "conf": 0.8640812635421753,
      "x1": 267.4757995605469,
      "y1": 88.94740295410156,
      "x2": 371.5302734375,
      "y2": 154.77745056152344
    },
    {
      "image_name": "test_130.jpg",
      "class_id": 1,
      "class_name": "Cracks",
      "conf": 0.8660192489624023,
      "x1": 269.6099548339844,
      "y1": 264.29632568359375,
      "x2": 404.2156677246094,
      "y2": 374.05615234375
    },
    {
      "image_name": "test_131.jpg",
      "class_id": 0,
      "class_name": "Rust",
      "conf": 0.8936811685562134,
      "x1": 407.9796447753906,
      "y1": 276.1751708984375,
      "x2": 466.2348327636719,
      "y2": 639.0
    },
    {
      "image_name": "test_131.jpg",
      "class_id": 0,
      "class_name": "Rust",
      "conf": 0.8641958832740784,
      "x1": 410.8645324707031,
      "y1": 0.3782539367675781,
      "x2": 461.1402587890625,
      "y2": 251.93008422851562
    },
    {
      "image_name": "test_132.jpg",
      "class_id": 0,
      "class_name": "Rust",
      "conf": 0.9074763655662537,
      "x1": 410.0304260253906,
      "y1": 412.503173828125,
      "x2": 464.138427734375,
      "y2": 639.0
    },
    {
      "image_name": "test_132.jpg",
      "class_id": 0,
      "class_name": "Rust",
      "conf": 0.8830344080924988,
      "x1": 409.15521240234375,
      "y1": 0.8637886047363281,
      "x2": 461.63653564453125,
      "y2": 217.85940551757812
    },
    {
      "image_name": "test_132.jpg",
      "class_id": 0,
      "class_name": "Rust",
      "conf": 0.8606036305427551,
      "x1": 411.8282470703125,
      "y1": 248.12509155273438,
      "x2": 461.31365966796875,
      "y2": 399.1644287109375
    },
    {
      "image_name": "test_133.jpg",
      "class_id": 0,
      "class_name": "Rust",
      "conf": 0.8749346137046814,
      "x1": 284.220947265625,
      "y1": 335.0684814453125,
      "x2": 347.2337646484375,
      "y2": 637.1522827148438
    },
    {
      "image_name": "test_133.jpg",
      "class_id": 0,
      "class_name": "Rust",
      "conf": 0.8583627939224243,
      "x1": 284.6188659667969,
      "y1": 9.685150146484375,
      "x2": 343.1869812011719,
      "y2": 317.6014099121094
    },
    {
      "image_name": "test_134.jpg",
      "class_id": 0,
      "class_name": "Rust",
      "conf": 0.8791467547416687,
      "x1": 284.1485900878906,
      "y1": 300.5000915527344,
      "x2": 348.3011779785156,
      "y2": 629.3312377929688
    },
    {
      "image_name": "test_134.jpg",
      "class_id": 0,
      "class_name": "Rust",
      "conf": 0.8606036305427551,
      "x1": 284.0434875488281,
      "y1": 0.46646881103515625,
      "x2": 343.4754638671875,
      "y2": 279.582275390625
    },
    {
      "image_name": "test_135.jpg",
      "class_id": 0,
      "class_name": "Rust",
      "conf": 0.8688268065452576,
      "x1": 337.48211669921875,
      "y1": 585.7179565429688,
      "x2": 504.7979736328125,
      "y2": 639.0
    },
    {
      "image_name": "test_136.jpg",
      "class_id": 0,
      "class_name": "Rust",
      "conf": 0.9184802770614624,
      "x1": 340.144775390625,
      "y1": 441.7489929199219,
      "x2": 503.37158203125,
      "y2": 522.70947265625
    },
    {
      "image_name": "test_137.jpg",
      "class_id": 0,
      "class_name": "Rust",
      "conf": 0.8714748620986938,
      "x1": 239.11923217773438,
      "y1": 585.5530395507812,
      "x2": 408.23443603515625,
      "y2": 639.0
    },
    {
      "image_name": "test_138.jpg",
      "class_id": 0,
      "class_name": "Rust",
      "conf": 0.8908652067184448,
      "x1": 255.7796630859375,
      "y1": 288.1138916015625,
      "x2": 385.46417236328125,
      "y2": 352.0322265625
    },
    {
      "image_name": "test_138.jpg",
      "class_id": 4,
      "class_name": "Pitting",
      "conf": 0.5994850993156433,
      "x1": 453.272705078125,
      "y1": 273.33734130859375,
      "x2": 467.99859619140625,
      "y2": 287.2045593261719
    },
    {
      "image_name": "test_139.jpg",
      "class_id": 4,
      "class_name": "Pitting",
      "conf": 0.8992984294891357,
      "x1": 344.95068359375,
      "y1": 140.1444854736328,
      "x2": 404.82928466796875,
      "y2": 191.58743286132812
    },
    {
      "image_name": "test_139.jpg",
      "class_id": 4,
      "class_name": "Pitting",
      "conf": 0.8836382627487183,
      "x1": 290.4268798828125,
      "y1": 299.9474182128906,
      "x2": 345.24383544921875,
      "y2": 347.48040771484375
    },
    {
      "image_name": "test_14.jpg",
      "class_id": 1,
      "class_name": "Cracks",
      "conf": 0.5964919328689575,
      "x1": 276.8116455078125,
      "y1": 273.7691955566406,
      "x2": 319.8648376464844,
      "y2": 476.8176574707031
    },
    {
      "image_name": "test_140.jpg",
      "class_id": 4,
      "class_name": "Pitting",
      "conf": 0.8940516710281372,
      "x1": 291.7362060546875,
      "y1": 293.2348937988281,
      "x2": 348.7965393066406,
      "y2": 347.45782470703125
    },
    {
      "image_name": "test_140.jpg",
      "class_id": 4,
      "class_name": "Pitting",
      "conf": 0.8608377575874329,
      "x1": 236.3549041748047,
      "y1": 454.7230529785156,
      "x2": 291.8561096191406,
      "y2": 500.63616943359375
    },
    {
      "image_name": "test_141.jpg",
      "class_id": 0,
      "class_name": "Rust",
      "conf": 0.9159594178199768,
      "x1": 241.485595703125,
      "y1": 440.5733947753906,
      "x2": 404.5843505859375,
      "y2": 522.6559448242188
    },
    {
      "image_name": "test_142.jpg",
      "class_id": 0,
      "class_name": "Rust",
      "conf": 0.8916224837303162,
      "x1": 255.77984619140625,
      "y1": 288.1768493652344,
      "x2": 385.37158203125,
      "y2": 352.1900329589844
    },
    {
      "image_name": "test_142.jpg",
      "class_id": 4,
      "class_name": "Pitting",
      "conf": 0.6059156656265259,
      "x1": 453.39117431640625,
      "y1": 273.19671630859375,
      "x2": 468.1145935058594,
      "y2": 287.05316162109375
    },
    {
      "image_name": "test_143.jpg",
      "class_id": 4,
      "class_name": "Pitting",
      "conf": 0.8844391107559204,
      "x1": 345.572509765625,
      "y1": 133.60858154296875,
      "x2": 404.15533447265625,
      "y2": 186.9202117919922
    },
    {
      "image_name": "test_143.jpg",
      "class_id": 4,
      "class_name": "Pitting",
      "conf": 0.87364661693573,
      "x1": 290.64300537109375,
      "y1": 294.4361267089844,
      "x2": 345.3721618652344,
      "y2": 341.8949890136719
    },
    {
      "image_name": "test_144.jpg",
      "class_id": 4,
      "class_name": "Pitting",
      "conf": 0.8885655403137207,
      "x1": 291.7842712402344,
      "y1": 292.8475341796875,
      "x2": 348.42694091796875,
      "y2": 347.289794921875
    },
    {
      "image_name": "test_144.jpg",
      "class_id": 4,
      "class_name": "Pitting",
      "conf": 0.8613050580024719,
      "x1": 236.5142822265625,
      "y1": 454.590087890625,
      "x2": 291.48565673828125,
      "y2": 501.0048522949219
    },
    {
      "image_name": "test_145.jpg",
      "class_id": 0,
      "class_name": "Rust",
      "conf": 0.8649961352348328,
      "x1": 21.480422973632812,
      "y1": 584.703369140625,
      "x2": 194.0877685546875,
      "y2": 639.0
    },
    {
      "image_name": "test_146.jpg",
      "class_id": 0,
      "class_name": "Rust",
      "conf": 0.8916224837303162,
      "x1": 229.47894287109375,
      "y1": 288.23980712890625,
      "x2": 357.91363525390625,
      "y2": 352.94573974609375
    },
    {
      "image_name": "test_146.jpg",
      "class_id": 4,
      "class_name": "Pitting",
      "conf": 0.6108598113059998,
      "x1": 423.9189147949219,
      "y1": 273.2708740234375,
      "x2": 438.9156799316406,
      "y2": 286.935302734375
    },
    {
      "image_name": "test_147.jpg",
      "class_id": 4,
      "class_name": "Pitting",
      "conf": 0.8992984294891357,
      "x1": 344.95068359375,
      "y1": 140.1444854736328,
      "x2": 404.82928466796875,
      "y2": 191.58743286132812
    },
    {
      "image_name": "test_147.jpg",
      "class_id": 4,
      "class_name": "Pitting",
      "conf": 0.8836382627487183,
      "x1": 290.4268798828125,
      "y1": 299.9474182128906,
      "x2": 345.24383544921875,
      "y2": 347.48040771484375
    },
    {
      "image_name": "test_148.jpg",
      "class_id": 4,
      "class_name": "Pitting",
      "conf": 0.8940516710281372,
      "x1": 291.7362060546875,
      "y1": 293.2348937988281,
      "x2": 348.7965393066406,
      "y2": 347.45782470703125
    },
    {
      "image_name": "test_148.jpg",
      "class_id": 4,
      "class_name": "Pitting",
      "conf": 0.8608377575874329,
      "x1": 236.3549041748047,
      "y1": 454.7230529785156,
      "x2": 291.8561096191406,
      "y2": 500.63616943359375
    },
    {
      "image_name": "test_149.jpg",
      "class_id": 0,
      "class_name": "Rust",
      "conf": 0.9139840602874756,
      "x1": 24.147544860839844,
      "y1": 440.3611145019531,
      "x2": 189.66481018066406,
      "y2": 523.0042114257812
    },
    {
      "image_name": "test_15.jpg",
      "class_id": 1,
      "class_name": "Cracks",
      "conf": 0.5192775726318359,
      "x1": 276.76226806640625,
      "y1": 1.013885498046875,
      "x2": 319.8224792480469,
      "y2": 221.36537170410156
    },
    {
      "image_name": "test_150.jpg",
      "class_id": 0,
      "class_name": "Rust",
      "conf": 0.8901033401489258,
      "x1": 229.16384887695312,
      "y1": 288.27117919921875,
      "x2": 357.71014404296875,
      "y2": 352.8834533691406
    },
    {
      "image_name": "test_150.jpg",
      "class_id": 4,
      "class_name": "Pitting",
      "conf": 0.6254380941390991,
      "x1": 424.0107727050781,
      "y1": 273.2000732421875,
      "x2": 438.9765319824219,
      "y2": 286.8058166503906
    },
    {
      "image_name": "test_151.jpg",
      "class_id": 4,
      "class_name": "Pitting",
      "conf": 0.8844391107559204,
      "x1": 345.572509765625,
      "y1": 133.60858154296875,
      "x2": 404.15533447265625,
      "y2": 186.9202117919922
    },
    {
      "image_name": "test_151.jpg",
      "class_id": 4,
      "class_name": "Pitting",
      "conf": 0.87364661693573,
      "x1": 290.64300537109375,
      "y1": 294.4361267089844,
      "x2": 345.3721618652344,
      "y2": 341.8949890136719
    },
    {
      "image_name": "test_152.jpg",
      "class_id": 4,
      "class_name": "Pitting",
      "conf": 0.8885655403137207,
      "x1": 291.7842712402344,
      "y1": 292.8475341796875,
      "x2": 348.42694091796875,
      "y2": 347.289794921875
    },
    {
      "image_name": "test_152.jpg",
      "class_id": 4,
      "class_name": "Pitting",
      "conf": 0.8613050580024719,
      "x1": 236.5142822265625,
      "y1": 454.590087890625,
      "x2": 291.48565673828125,
      "y2": 501.0048522949219
    },
    {
      "image_name": "test_157.jpg",
      "class_id": 4,
      "class_name": "Pitting",
      "conf": 0.651576578617096,
      "x1": 208.74282836914062,
      "y1": 431.216796875,
      "x2": 401.1377258300781,
      "y2": 635.8487548828125
    },
    {
      "image_name": "test_158.jpg",
      "class_id": 4,
      "class_name": "Pitting",
      "conf": 0.8296300768852234,
      "x1": 203.65487670898438,
      "y1": 198.9209442138672,
      "x2": 402.5445861816406,
      "y2": 456.12005615234375
    },
    {
      "image_name": "test_159.jpg",
      "class_id": 4,
      "class_name": "Pitting",
      "conf": 0.8378854393959045,
      "x1": 231.5835418701172,
      "y1": 228.63856506347656,
      "x2": 394.08709716796875,
      "y2": 435.3555908203125
    },
    {
      "image_name": "test_16.jpg",
      "class_id": 1,
      "class_name": "Cracks",
      "conf": 0.7655933499336243,
      "x1": 316.5987854003906,
      "y1": 324.353515625,
      "x2": 359.16973876953125,
      "y2": 495.0546875
    },
    {
      "image_name": "test_160.jpg",
      "class_id": 4,
      "class_name": "Pitting",
      "conf": 0.8675976395606995,
      "x1": 233.7463836669922,
      "y1": 233.13998413085938,
      "x2": 386.2616271972656,
      "y2": 424.8614196777344
    },
    {
      "image_name": "test_161.jpg",
      "class_id": 4,
      "class_name": "Pitting",
      "conf": 0.8674854636192322,
      "x1": 236.13320922851562,
      "y1": 174.42991638183594,
      "x2": 384.9267272949219,
      "y2": 368.0541687011719
    },
    {
      "image_name": "test_162.jpg",
      "class_id": 4,
      "class_name": "Pitting",
      "conf": 0.8566924333572388,
      "x1": 233.64524841308594,
      "y1": 227.8458709716797,
      "x2": 403.74249267578125,
      "y2": 435.258544921875
    },
    {
      "image_name": "test_163.jpg",
      "class_id": 4,
      "class_name": "Pitting",
      "conf": 0.8366879820823669,
      "x1": 233.5514373779297,
      "y1": 231.62103271484375,
      "x2": 387.5859375,
      "y2": 423.66925048828125
    },
    {
      "image_name": "test_164.jpg",
      "class_id": 4,
      "class_name": "Pitting",
      "conf": 0.8485961556434631,
      "x1": 235.07281494140625,
      "y1": 172.08792114257812,
      "x2": 387.2578430175781,
      "y2": 365.78106689453125
    },
    {
      "image_name": "test_167.jpg",
      "class_id": 4,
      "class_name": "Pitting",
      "conf": 0.38890811800956726,
      "x1": 210.53480529785156,
      "y1": 221.99612426757812,
      "x2": 392.9269714355469,
      "y2": 450.7318420410156
    },
    {
      "image_name": "test_169.jpg",
      "class_id": 4,
      "class_name": "Pitting",
      "conf": 0.8485961556434631,
      "x1": 95.63377380371094,
      "y1": 506.5817565917969,
      "x2": 339.3978271484375,
      "y2": 639.0
    },
    {
      "image_name": "test_17.jpg",
      "class_id": 1,
      "class_name": "Cracks",
      "conf": 0.7585106492042542,
      "x1": 316.3130798339844,
      "y1": 75.32979583740234,
      "x2": 357.7686767578125,
      "y2": 236.2938232421875
    },
    {
      "image_name": "test_170.jpg",
      "class_id": 4,
      "class_name": "Pitting",
      "conf": 0.8725647330284119,
      "x1": 107.08375549316406,
      "y1": 31.959335327148438,
      "x2": 344.437255859375,
      "y2": 344.48193359375
    },
    {
      "image_name": "test_171.jpg",
      "class_id": 1,
      "class_name": "Cracks",
      "conf": 0.7388575673103333,
      "x1": 274.8562927246094,
      "y1": 322.7823181152344,
      "x2": 421.9607849121094,
      "y2": 395.41534423828125
    },
    {
      "image_name": "test_171.jpg",
      "class_id": 1,
      "class_name": "Cracks",
      "conf": 0.49247798323631287,
      "x1": 276.4743957519531,
      "y1": 570.5926513671875,
      "x2": 385.33074951171875,
      "y2": 639.0
    },
    {
      "image_name": "test_172.jpg",
      "class_id": 2,
      "class_name": "patches",
      "conf": 0.7745833992958069,
      "x1": 395.9753112792969,
      "y1": 1.45001220703125,
      "x2": 638.752197265625,
      "y2": 255.1361541748047
    },
    {
      "image_name": "test_177.jpg",
      "class_id": 1,
      "class_name": "Cracks",
      "conf": 0.7123322486877441,
      "x1": 274.90667724609375,
      "y1": 322.8031311035156,
      "x2": 421.2460021972656,
      "y2": 395.9770812988281
    },
    {
      "image_name": "test_177.jpg",
      "class_id": 1,
      "class_name": "Cracks",
      "conf": 0.48840540647506714,
      "x1": 275.0090026855469,
      "y1": 571.2545166015625,
      "x2": 385.7417907714844,
      "y2": 639.0
    },
    {
      "image_name": "test_178.jpg",
      "class_id": 2,
      "class_name": "patches",
      "conf": 0.8070047497749329,
      "x1": 396.70904541015625,
      "y1": 1.3526611328125,
      "x2": 638.572021484375,
      "y2": 256.171142578125
    },
    {
      "image_name": "test_18.jpg",
      "class_id": 2,
      "class_name": "patches",
      "conf": 0.9196425676345825,
      "x1": 325.50201416015625,
      "y1": 520.0792846679688,
      "x2": 450.47528076171875,
      "y2": 627.0899047851562
    },
    {
      "image_name": "test_185.jpg",
      "class_id": 0,
      "class_name": "Rust",
      "conf": 0.8528128862380981,
      "x1": 193.1561279296875,
      "y1": 183.72532653808594,
      "x2": 444.81732177734375,
      "y2": 447.78143310546875
    },
    {
      "image_name": "test_186.jpg",
      "class_id": 0,
      "class_name": "Rust",
      "conf": 0.8528128862380981,
      "x1": 193.1561279296875,
      "y1": 183.72532653808594,
      "x2": 444.81732177734375,
      "y2": 447.78143310546875
    },
    {
      "image_name": "test_187.jpg",
      "class_id": 1,
      "class_name": "Cracks",
      "conf": 0.8791467547416687,
      "x1": 295.6280517578125,
      "y1": 337.074462890625,
      "x2": 613.1616821289062,
      "y2": 638.524658203125
    },
    {
      "image_name": "test_187.jpg",
      "class_id": 1,
      "class_name": "Cracks",
      "conf": 0.5305253267288208,
      "x1": 0.0,
      "y1": 318.662109375,
      "x2": 277.51171875,
      "y2": 639.0
    },
    {
      "image_name": "test_188.jpg",
      "class_id": 1,
      "class_name": "Cracks",
      "conf": 0.8766343593597412,
      "x1": 232.6961669921875,
      "y1": 335.517578125,
      "x2": 546.5919189453125,
      "y2": 638.9544067382812
    },
    {
      "image_name": "test_188.jpg",
      "class_id": 1,
      "class_name": "Cracks",
      "conf": 0.44504714012145996,
      "x1": 0.0,
      "y1": 266.3559265136719,
      "x2": 164.5042724609375,
      "y2": 639.0
    },
    {
      "image_name": "test_189.jpg",
      "class_id": 1,
      "class_name": "Cracks",
      "conf": 0.8431217074394226,
      "x1": 436.01885986328125,
      "y1": 336.2625427246094,
      "x2": 638.8690185546875,
      "y2": 639.0
    },
    {
      "image_name": "test_19.jpg",
      "class_id": 2,
      "class_name": "patches",
      "conf": 0.9296960830688477,
      "x1": 324.95037841796875,
      "y1": 262.12713623046875,
      "x2": 450.8240661621094,
      "y2": 365.4265441894531
    },
    {
      "image_name": "test_190.jpg",
      "class_id": 1,
      "class_name": "Cracks",
      "conf": 0.9212159514427185,
      "x1": 441.3109436035156,
      "y1": 0.0,
      "x2": 639.0,
      "y2": 267.4314270019531
    },
    {
      "image_name": "test_191.jpg",
      "class_id": 1,
      "class_name": "Cracks",
      "conf": 0.8622356653213501,
      "x1": 362.01995849609375,
      "y1": 306.4371032714844,
      "x2": 639.0,
      "y2": 555.240478515625
    },
    {
      "image_name": "test_192.jpg",
      "class_id": 1,
      "class_name": "Cracks",
      "conf": 0.879871129989624,
      "x1": 0.0,
      "y1": 299.47259521484375,
      "x2": 321.1072082519531,
      "y2": 542.7189331054688
    },
    {
      "image_name": "test_193.jpg",
      "class_id": 1,
      "class_name": "Cracks",
      "conf": 0.7853085398674011,
      "x1": 501.6827697753906,
      "y1": 0.0,
      "x2": 639.0,
      "y2": 288.0263671875
    },
    {
      "image_name": "test_194.jpg",
      "class_id": 1,
      "class_name": "Cracks",
      "conf": 0.843508780002594,
      "x1": 231.06329345703125,
      "y1": 239.1372833251953,
      "x2": 639.0,
      "y2": 522.9874877929688
    },
    {
      "image_name": "test_195.jpg",
      "class_id": 1,
      "class_name": "Cracks",
      "conf": 0.8996515870094299,
      "x1": 49.43402099609375,
      "y1": 4.7468109130859375,
      "x2": 441.1943359375,
      "y2": 293.7498779296875
    },
    {
      "image_name": "test_195.jpg",
      "class_id": 1,
      "class_name": "Cracks",
      "conf": 0.6904547214508057,
      "x1": 109.19493103027344,
      "y1": 435.5486755371094,
      "x2": 545.7308349609375,
      "y2": 639.0
    },
    {
      "image_name": "test_196.jpg",
      "class_id": 1,
      "class_name": "Cracks",
      "conf": 0.8659058809280396,
      "x1": 0.0,
      "y1": 239.6322479248047,
      "x2": 225.38084411621094,
      "y2": 491.1654968261719
    },
    {
      "image_name": "test_197.jpg",
      "class_id": 1,
      "class_name": "Cracks",
      "conf": 0.8936811685562134,
      "x1": 41.57048034667969,
      "y1": 489.2489013671875,
      "x2": 436.47845458984375,
      "y2": 639.0
    },
    {
      "image_name": "test_198.jpg",
      "class_id": 2,
      "class_name": "patches",
      "conf": 0.8949732184410095,
      "x1": 237.32598876953125,
      "y1": 522.5424194335938,
      "x2": 353.2517395019531,
      "y2": 639.0
    },
    {
      "image_name": "test_199.jpg",
      "class_id": 2,
      "class_name": "patches",
      "conf": 0.9029524326324463,
      "x1": 238.77565002441406,
      "y1": 43.363739013671875,
      "x2": 354.5141906738281,
      "y2": 163.3801727294922
    },
    {
      "image_name": "test_2.jpg",
      "class_id": 2,
      "class_name": "patches",
      "conf": 0.8085212111473083,
      "x1": 112.64386749267578,
      "y1": 593.8740844726562,
      "x2": 238.20599365234375,
      "y2": 639.0
    },
    {
      "image_name": "test_20.jpg",
      "class_id": 2,
      "class_name": "patches",
      "conf": 0.84065181016922,
      "x1": 0.0,
      "y1": 500.9105224609375,
      "x2": 54.42112731933594,
      "y2": 624.9891967773438
    },
    {
      "image_name": "test_200.jpg",
      "class_id": 1,
      "class_name": "Cracks",
      "conf": 0.8834372758865356,
      "x1": 153.4444580078125,
      "y1": 0.8365859985351562,
      "x2": 310.02130126953125,
      "y2": 174.11923217773438
    },
    {
      "image_name": "test_201.jpg",
      "class_id": 1,
      "class_name": "Cracks",
      "conf": 0.8846386671066284,
      "x1": 88.73141479492188,
      "y1": 0.647186279296875,
      "x2": 246.10647583007812,
      "y2": 174.55706787109375
    },
    {
      "image_name": "test_202.jpg",
      "class_id": 4,
      "class_name": "Pitting",
      "conf": 0.7991290092468262,
      "x1": 260.44610595703125,
      "y1": 225.58309936523438,
      "x2": 396.853759765625,
      "y2": 415.9036560058594
    },
    {
      "image_name": "test_203.jpg",
      "class_id": 4,
      "class_name": "Pitting",
      "conf": 0.819749116897583,
      "x1": 165.24746704101562,
      "y1": 229.68173217773438,
      "x2": 330.707763671875,
      "y2": 420.2463073730469
    },
    {
      "image_name": "test_204.jpg",
      "class_id": 4,
      "class_name": "Pitting",
      "conf": 0.8241790533065796,
      "x1": 28.452239990234375,
      "y1": 229.68002319335938,
      "x2": 201.47921752929688,
      "y2": 420.9673156738281
    },
    {
      "image_name": "test_205.jpg",
      "class_id": 4,
      "class_name": "Pitting",
      "conf": 0.8611882925033569,
      "x1": 486.1771545410156,
      "y1": 225.92941284179688,
      "x2": 639.0,
      "y2": 419.0067443847656
    },
    {
      "image_name": "test_206.jpg",
      "class_id": 4,
      "class_name": "Pitting",
      "conf": 0.8116759657859802,
      "x1": 248.93145751953125,
      "y1": 238.15451049804688,
      "x2": 414.5878601074219,
      "y2": 420.8458557128906
    },
    {
      "image_name": "test_207.jpg",
      "class_id": 4,
      "class_name": "Pitting",
      "conf": 0.8020908832550049,
      "x1": 219.0726776123047,
      "y1": 238.9901123046875,
      "x2": 378.7286376953125,
      "y2": 420.09686279296875
    },
    {
      "image_name": "test_208.jpg",
      "class_id": 0,
      "class_name": "Rust",
      "conf": 0.9017477631568909,
      "x1": 511.3841857910156,
      "y1": 502.9848937988281,
      "x2": 619.8338623046875,
      "y2": 639.0
    },
    {
      "image_name": "test_209.jpg",
      "class_id": 0,
      "class_name": "Rust",
      "conf": 0.9043130874633789,
      "x1": 512.8200073242188,
      "y1": 25.16327667236328,
      "x2": 614.2186889648438,
      "y2": 206.35304260253906
    },
    {
      "image_name": "test_21.jpg",
      "class_id": 2,
      "class_name": "patches",
      "conf": 0.8340016603469849,
      "x1": 0.0,
      "y1": 256.80633544921875,
      "x2": 56.140235900878906,
      "y2": 381.6695861816406
    },
    {
      "image_name": "test_21.jpg",
      "class_id": 1,
      "class_name": "Cracks",
      "conf": 0.6059739589691162,
      "x1": 563.3515625,
      "y1": 410.3897705078125,
      "x2": 591.17822265625,
      "y2": 525.000732421875
    },
    {
      "image_name": "test_210.jpg",
      "class_id": 4,
      "class_name": "Pitting",
      "conf": 0.8690492510795593,
      "x1": 319.28753662109375,
      "y1": 477.24591064453125,
      "x2": 499.149658203125,
      "y2": 611.41357421875
    },
    {
      "image_name": "test_211.jpg",
      "class_id": 2,
      "class_name": "patches",
      "conf": 0.8632764220237732,
      "x1": 2.05548095703125,
      "y1": 376.62249755859375,
      "x2": 261.4714660644531,
      "y2": 639.0
    },
    {
      "image_name": "test_212.jpg",
      "class_id": 2,
      "class_name": "patches",
      "conf": 0.8927496671676636,
      "x1": 0.0667877197265625,
      "y1": 0.37625885009765625,
      "x2": 264.24383544921875,
      "y2": 226.01547241210938
    },
    {
      "image_name": "test_213.jpg",
      "class_id": 4,
      "class_name": "Pitting",
      "conf": 0.8998278379440308,
      "x1": 324.85089111328125,
      "y1": 108.84236907958984,
      "x2": 498.82916259765625,
      "y2": 244.2448272705078
    },
    {
      "image_name": "test_214.jpg",
      "class_id": 4,
      "class_name": "Pitting",
      "conf": 0.8677098155021667,
      "x1": 231.02294921875,
      "y1": 477.2440185546875,
      "x2": 412.0889892578125,
      "y2": 612.225341796875
    },
    {
      "image_name": "test_215.jpg",
      "class_id": 2,
      "class_name": "patches",
      "conf": 0.8960696458816528,
      "x1": 0.0614471435546875,
      "y1": 374.942626953125,
      "x2": 196.02694702148438,
      "y2": 639.0
    },
    {
      "image_name": "test_216.jpg",
      "class_id": 2,
      "class_name": "patches",
      "conf": 0.9008791446685791,
      "x1": 0.8704376220703125,
      "y1": 0.02933502197265625,
      "x2": 196.9893035888672,
      "y2": 224.94024658203125
    },
    {
      "image_name": "test_217.jpg",
      "class_id": 4,
      "class_name": "Pitting",
      "conf": 0.8908652067184448,
      "x1": 236.4793701171875,
      "y1": 108.56459045410156,
      "x2": 413.11749267578125,
      "y2": 243.2828826904297
    },
    {
      "image_name": "test_218.jpg",
      "class_id": 0,
      "class_name": "Rust",
      "conf": 0.9003546833992004,
      "x1": 31.573745727539062,
      "y1": 505.5963134765625,
      "x2": 137.91534423828125,
      "y2": 639.0
    },
    {
      "image_name": "test_218.jpg",
      "class_id": 2,
      "class_name": "patches",
      "conf": 0.7018153071403503,
      "x1": 442.1087646484375,
      "y1": 373.2596435546875,
      "x2": 639.0,
      "y2": 639.0
    },
    {
      "image_name": "test_218.jpg",
      "class_id": 4,
      "class_name": "Pitting",
      "conf": 0.7006900310516357,
      "x1": 216.26380920410156,
      "y1": 553.4244995117188,
      "x2": 257.38946533203125,
      "y2": 593.2313232421875
    },
    {
      "image_name": "test_218.jpg",
      "class_id": 0,
      "class_name": "Rust",
      "conf": 0.4685474932193756,
      "x1": 440.9689636230469,
      "y1": 374.24761962890625,
      "x2": 638.9454345703125,
      "y2": 639.0
    },
    {
      "image_name": "test_219.jpg",
      "class_id": 0,
      "class_name": "Rust",
      "conf": 0.9003546833992004,
      "x1": 31.573745727539062,
      "y1": 505.5963134765625,
      "x2": 137.91534423828125,
      "y2": 639.0
    },
    {
      "image_name": "test_219.jpg",
      "class_id": 2,
      "class_name": "patches",
      "conf": 0.7018153071403503,
      "x1": 442.1087646484375,
      "y1": 373.2596435546875,
      "x2": 639.0,
      "y2": 639.0
    },
    {
      "image_name": "test_219.jpg",
      "class_id": 4,
      "class_name": "Pitting",
      "conf": 0.7006900310516357,
      "x1": 216.26380920410156,
      "y1": 553.4244995117188,
      "x2": 257.38946533203125,
      "y2": 593.2313232421875
    },
    {
      "image_name": "test_219.jpg",
      "class_id": 0,
      "class_name": "Rust",
      "conf": 0.4685474932193756,
      "x1": 440.9689636230469,
      "y1": 374.24761962890625,
      "x2": 638.9454345703125,
      "y2": 639.0
    },
    {
      "image_name": "test_220.jpg",
      "class_id": 4,
      "class_name": "Pitting",
      "conf": 0.8964328765869141,
      "x1": 204.32742309570312,
      "y1": 217.1932373046875,
      "x2": 435.9915771484375,
      "y2": 426.7554626464844
    },
    {
      "image_name": "test_221.jpg",
      "class_id": 0,
      "class_name": "Rust",
      "conf": 0.9091032147407532,
      "x1": 33.571434020996094,
      "y1": 27.350425720214844,
      "x2": 133.6654052734375,
      "y2": 206.01596069335938
    },
    {
      "image_name": "test_221.jpg",
      "class_id": 4,
      "class_name": "Pitting",
      "conf": 0.7150261998176575,
      "x1": 215.98736572265625,
      "y1": 73.70320892333984,
      "x2": 257.5405578613281,
      "y2": 113.09269714355469
    },
    {
      "image_name": "test_221.jpg",
      "class_id": 2,
      "class_name": "patches",
      "conf": 0.7019174098968506,
      "x1": 440.66143798828125,
      "y1": 0.0,
      "x2": 639.0,
      "y2": 233.40133666992188
    },
    {
      "image_name": "test_221.jpg",
      "class_id": 0,
      "class_name": "Rust",
      "conf": 0.6637779474258423,
      "x1": 445.0550842285156,
      "y1": 0.0,
      "x2": 639.0,
      "y2": 232.0252227783203
    },
    {
      "image_name": "test_222.jpg",
      "class_id": 4,
      "class_name": "Pitting",
      "conf": 0.8964328765869141,
      "x1": 204.32742309570312,
      "y1": 217.1932373046875,
      "x2": 435.9915771484375,
      "y2": 426.7554626464844
    },
    {
      "image_name": "test_223.jpg",
      "class_id": 0,
      "class_name": "Rust",
      "conf": 0.9192084670066833,
      "x1": 459.2641906738281,
      "y1": 356.0433349609375,
      "x2": 557.772216796875,
      "y2": 535.9674072265625
    },
    {
      "image_name": "test_224.jpg",
      "class_id": 0,
      "class_name": "Rust",
      "conf": 0.8872045874595642,
      "x1": 383.0457763671875,
      "y1": 0.0,
      "x2": 529.2008056640625,
      "y2": 77.65103149414062
    },
    {
      "image_name": "test_225.jpg",
      "class_id": 4,
      "class_name": "Pitting",
      "conf": 0.8653379082679749,
      "x1": 390.53082275390625,
      "y1": 263.4622802734375,
      "x2": 575.5241088867188,
      "y2": 377.12353515625
    },
    {
      "image_name": "test_226.jpg",
      "class_id": 2,
      "class_name": "patches",
      "conf": 0.9068183302879333,
      "x1": 0.5015411376953125,
      "y1": 227.7944793701172,
      "x2": 215.28302001953125,
      "y2": 569.7081909179688
    },
    {
      "image_name": "test_227.jpg",
      "class_id": 4,
      "class_name": "Pitting",
      "conf": 0.8583627939224243,
      "x1": 274.1534423828125,
      "y1": 264.76763916015625,
      "x2": 453.7545166015625,
      "y2": 377.3074035644531
    },
    {
      "image_name": "test_228.jpg",
      "class_id": 2,
      "class_name": "patches",
      "conf": 0.9194981455802917,
      "x1": 0.0,
      "y1": 235.01344299316406,
      "x2": 148.49021911621094,
      "y2": 571.6260375976562
    },
    {
      "image_name": "test_229.jpg",
      "class_id": 2,
      "class_name": "patches",
      "conf": 0.8891444206237793,
      "x1": 420.826416015625,
      "y1": 240.9204559326172,
      "x2": 639.0,
      "y2": 569.730224609375
    },
    {
      "image_name": "test_229.jpg",
      "class_id": 0,
      "class_name": "Rust",
      "conf": 0.8844391107559204,
      "x1": 0.6577644348144531,
      "y1": 350.9334716796875,
      "x2": 77.73902893066406,
      "y2": 536.9830322265625
    },
    {
      "image_name": "test_229.jpg",
      "class_id": 4,
      "class_name": "Pitting",
      "conf": 0.7096232175827026,
      "x1": 163.63865661621094,
      "y1": 400.52288818359375,
      "x2": 202.99717712402344,
      "y2": 437.6608581542969
    },
    {
      "image_name": "test_23.jpg",
      "class_id": 1,
      "class_name": "Cracks",
      "conf": 0.703345775604248,
      "x1": 72.89308166503906,
      "y1": 1.5434646606445312,
      "x2": 504.0466003417969,
      "y2": 220.09902954101562
    },
    {
      "image_name": "test_230.jpg",
      "class_id": 2,
      "class_name": "patches",
      "conf": 0.8891444206237793,
      "x1": 420.826416015625,
      "y1": 240.9204559326172,
      "x2": 639.0,
      "y2": 569.730224609375
    },
    {
      "image_name": "test_230.jpg",
      "class_id": 0,
      "class_name": "Rust",
      "conf": 0.8844391107559204,
      "x1": 0.6577644348144531,
      "y1": 350.9334716796875,
      "x2": 77.73902893066406,
      "y2": 536.9830322265625
    },
    {
      "image_name": "test_230.jpg",
      "class_id": 4,
      "class_name": "Pitting",
      "conf": 0.7096232175827026,
      "x1": 163.63865661621094,
      "y1": 400.52288818359375,
      "x2": 202.99717712402344,
      "y2": 437.6608581542969
    },
    {
      "image_name": "test_231.jpg",
      "class_id": 4,
      "class_name": "Pitting",
      "conf": 0.8842393159866333,
      "x1": 222.61972045898438,
      "y1": 201.4486083984375,
      "x2": 424.8237609863281,
      "y2": 425.4884033203125
    },
    {
      "image_name": "test_232.jpg",
      "class_id": 0,
      "class_name": "Rust",
      "conf": 0.9196425676345825,
      "x1": 0.5336837768554688,
      "y1": 0.0,
      "x2": 125.84750366210938,
      "y2": 98.73554992675781
    },
    {
      "image_name": "test_233.jpg",
      "class_id": 2,
      "class_name": "patches",
      "conf": 0.8703770637512207,
      "x1": 397.783935546875,
      "y1": 0.0,
      "x2": 639.0,
      "y2": 84.55477905273438
    },
    {
      "image_name": "test_233.jpg",
      "class_id": 0,
      "class_name": "Rust",
      "conf": 0.8411743640899658,
      "x1": 0.5074501037597656,
      "y1": 0.32955169677734375,
      "x2": 74.67101287841797,
      "y2": 58.10897445678711
    },
    {
      "image_name": "test_234.jpg",
      "class_id": 4,
      "class_name": "Pitting",
      "conf": 0.922062337398529,
      "x1": 237.54763793945312,
      "y1": 232.75799560546875,
      "x2": 403.25921630859375,
      "y2": 409.7426452636719
    },
    {
      "image_name": "test_235.jpg",
      "class_id": 4,
      "class_name": "Pitting",
      "conf": 0.892375111579895,
      "x1": 330.2477111816406,
      "y1": 211.57183837890625,
      "x2": 535.9393920898438,
      "y2": 435.4819641113281
    },
    {
      "image_name": "test_236.jpg",
      "class_id": 4,
      "class_name": "Pitting",
      "conf": 0.9184802770614624,
      "x1": 235.64944458007812,
      "y1": 150.47250366210938,
      "x2": 402.3328857421875,
      "y2": 327.6468505859375
    },
    {
      "image_name": "test_237.jpg",
      "class_id": 4,
      "class_name": "Pitting",
      "conf": 0.892375111579895,
      "x1": 330.2477111816406,
      "y1": 211.57183837890625,
      "x2": 535.9393920898438,
      "y2": 435.4819641113281
    },
    {
      "image_name": "test_238.jpg",
      "class_id": 4,
      "class_name": "Pitting",
      "conf": 0.7611836194992065,
      "x1": 206.14100646972656,
      "y1": 350.0060729980469,
      "x2": 436.6353454589844,
      "y2": 570.9651489257812
    },
    {
      "image_name": "test_239.jpg",
      "class_id": 3,
      "class_name": "Scratches",
      "conf": 0.709019124507904,
      "x1": 0.3881034851074219,
      "y1": 396.6842346191406,
      "x2": 60.92393112182617,
      "y2": 613.5923461914062
    },
    {
      "image_name": "test_240.jpg",
      "class_id": 3,
      "class_name": "Scratches",
      "conf": 0.902265727519989,
      "x1": 337.53411865234375,
      "y1": 400.22406005859375,
      "x2": 539.1121826171875,
      "y2": 533.6990966796875
    },
    {
      "image_name": "test_241.jpg",
      "class_id": 3,
      "class_name": "Scratches",
      "conf": 0.5567610859870911,
      "x1": 336.3257141113281,
      "y1": 0.5503005981445312,
      "x2": 599.0982666015625,
      "y2": 46.84477233886719
    },
    {
      "image_name": "test_242.jpg",
      "class_id": 4,
      "class_name": "Pitting",
      "conf": 0.7876046895980835,
      "x1": 354.16192626953125,
      "y1": 279.8494873046875,
      "x2": 487.1916198730469,
      "y2": 428.5937194824219
    },
    {
      "image_name": "test_242.jpg",
      "class_id": 4,
      "class_name": "Pitting",
      "conf": 0.7439128756523132,
      "x1": 0.0,
      "y1": 213.1666717529297,
      "x2": 53.15373992919922,
      "y2": 417.0255126953125
    },
    {
      "image_name": "test_243.jpg",
      "class_id": 4,
      "class_name": "Pitting",
      "conf": 0.898944079875946,
      "x1": 219.0352020263672,
      "y1": 210.50808715820312,
      "x2": 421.0868835449219,
      "y2": 436.4239807128906
    },
    {
      "image_name": "test_244.jpg",
      "class_id": 4,
      "class_name": "Pitting",
      "conf": 0.879871129989624,
      "x1": 212.1732940673828,
      "y1": 212.77786254882812,
      "x2": 401.97674560546875,
      "y2": 432.26556396484375
    },
    {
      "image_name": "test_245.jpg",
      "class_id": 4,
      "class_name": "Pitting",
      "conf": 0.7550956010818481,
      "x1": 204.89285278320312,
      "y1": 497.6579284667969,
      "x2": 429.4704895019531,
      "y2": 639.0
    },
    {
      "image_name": "test_246.jpg",
      "class_id": 4,
      "class_name": "Pitting",
      "conf": 0.8483450412750244,
      "x1": 356.2470397949219,
      "y1": 197.7794189453125,
      "x2": 487.6509094238281,
      "y2": 346.5751953125
    },
    {
      "image_name": "test_246.jpg",
      "class_id": 4,
      "class_name": "Pitting",
      "conf": 0.7749242186546326,
      "x1": 0.10281562805175781,
      "y1": 148.37884521484375,
      "x2": 52.50255584716797,
      "y2": 332.41119384765625
    },
    {
      "image_name": "test_247.jpg",
      "class_id": 4,
      "class_name": "Pitting",
      "conf": 0.898944079875946,
      "x1": 219.0352020263672,
      "y1": 210.50808715820312,
      "x2": 421.0868835449219,
      "y2": 436.4239807128906
    },
    {
      "image_name": "test_248.jpg",
      "class_id": 4,
      "class_name": "Pitting",
      "conf": 0.879871129989624,
      "x1": 212.1732940673828,
      "y1": 212.77786254882812,
      "x2": 401.97674560546875,
      "y2": 432.26556396484375
    },
    {
      "image_name": "test_249.jpg",
      "class_id": 4,
      "class_name": "Pitting",
      "conf": 0.7184956669807434,
      "x1": 252.73263549804688,
      "y1": 228.18150329589844,
      "x2": 396.6488342285156,
      "y2": 411.5511474609375
    },
    {
      "image_name": "test_250.jpg",
      "class_id": 2,
      "class_name": "patches",
      "conf": 0.8551267385482788,
      "x1": 593.21875,
      "y1": 498.16064453125,
      "x2": 639.0,
      "y2": 639.0
    },
    {
      "image_name": "test_251.jpg",
      "class_id": 2,
      "class_name": "patches",
      "conf": 0.885433554649353,
      "x1": 547.754150390625,
      "y1": 334.5074462890625,
      "x2": 639.0,
      "y2": 492.845947265625
    },
    {
      "image_name": "test_251.jpg",
      "class_id": 2,
      "class_name": "patches",
      "conf": 0.8554893136024475,
      "x1": 594.209716796875,
      "y1": 18.5025634765625,
      "x2": 639.0,
      "y2": 198.91500854492188
    },
    {
      "image_name": "test_252.jpg",
      "class_id": 2,
      "class_name": "patches",
      "conf": 0.87364661693573,
      "x1": 526.6380004882812,
      "y1": 500.7583923339844,
      "x2": 603.816162109375,
      "y2": 639.0
    },
    {
      "image_name": "test_253.jpg",
      "class_id": 2,
      "class_name": "patches",
      "conf": 0.8856314420700073,
      "x1": 482.40447998046875,
      "y1": 332.7071533203125,
      "x2": 617.4996337890625,
      "y2": 491.8353271484375
    },
    {
      "image_name": "test_253.jpg",
      "class_id": 2,
      "class_name": "patches",
      "conf": 0.8551267385482788,
      "x1": 527.3737182617188,
      "y1": 22.802886962890625,
      "x2": 599.35205078125,
      "y2": 196.91844177246094
    },
    {
      "image_name": "test_254.jpg",
      "class_id": 2,
      "class_name": "patches",
      "conf": 0.5000271797180176,
      "x1": 617.0680541992188,
      "y1": 512.7196044921875,
      "x2": 639.0,
      "y2": 639.0
    },
    {
      "image_name": "test_255.jpg",
      "class_id": 2,
      "class_name": "patches",
      "conf": 0.880591869354248,
      "x1": 580.5996704101562,
      "y1": 356.0633239746094,
      "x2": 639.0,
      "y2": 512.1281127929688
    },
    {
      "image_name": "test_255.jpg",
      "class_id": 2,
      "class_name": "patches",
      "conf": 0.6344300508499146,
      "x1": 615.3982543945312,
      "y1": 29.057823181152344,
      "x2": 639.0,
      "y2": 209.889892578125
    },
    {
      "image_name": "test_256.jpg",
      "class_id": 2,
      "class_name": "patches",
      "conf": 0.8936811685562134,
      "x1": 548.8257446289062,
      "y1": 516.7385864257812,
      "x2": 625.8546752929688,
      "y2": 639.0
    },
    {
      "image_name": "test_257.jpg",
      "class_id": 2,
      "class_name": "patches",
      "conf": 0.9130582809448242,
      "x1": 513.5542602539062,
      "y1": 350.7092590332031,
      "x2": 638.5943603515625,
      "y2": 516.1533203125
    },
    {
      "image_name": "test_257.jpg",
      "class_id": 2,
      "class_name": "patches",
      "conf": 0.8469578623771667,
      "x1": 548.8817749023438,
      "y1": 36.711647033691406,
      "x2": 624.3284301757812,
      "y2": 215.25404357910156
    },
    {
      "image_name": "test_258.jpg",
      "class_id": 2,
      "class_name": "patches",
      "conf": 0.38041362166404724,
      "x1": 504.69122314453125,
      "y1": 0.0,
      "x2": 639.0,
      "y2": 41.611385345458984
    },
    {
      "image_name": "test_259.jpg",
      "class_id": 2,
      "class_name": "patches",
      "conf": 0.8568122982978821,
      "x1": 3.66021728515625,
      "y1": 447.6932373046875,
      "x2": 403.9191589355469,
      "y2": 639.0
    },
    {
      "image_name": "test_26.jpg",
      "class_id": 1,
      "class_name": "Cracks",
      "conf": 0.6641048192977905,
      "x1": 0.0,
      "y1": 2.2673110961914062,
      "x2": 340.555419921875,
      "y2": 203.67396545410156
    },
    {
      "image_name": "test_260.jpg",
      "class_id": 2,
      "class_name": "patches",
      "conf": 0.8124212622642517,
      "x1": 0.568267822265625,
      "y1": 0.16880035400390625,
      "x2": 375.3006591796875,
      "y2": 210.7802734375
    },
    {
      "image_name": "test_261.jpg",
      "class_id": 3,
      "class_name": "Scratches",
      "conf": 0.8858291506767273,
      "x1": 102.04421997070312,
      "y1": 8.56085205078125,
      "x2": 332.2057800292969,
      "y2": 639.0
    },
    {
      "image_name": "test_261.jpg",
      "class_id": 3,
      "class_name": "Scratches",
      "conf": 0.6557770371437073,
      "x1": 361.09375,
      "y1": 0.0,
      "x2": 639.0,
      "y2": 614.0438232421875
    },
    {
      "image_name": "test_262.jpg",
      "class_id": 4,
      "class_name": "Pitting",
      "conf": 0.8362873792648315,
      "x1": 503.73492431640625,
      "y1": 220.6245880126953,
      "x2": 637.61083984375,
      "y2": 431.42877197265625
    },
    {
      "image_name": "test_263.jpg",
      "class_id": 4,
      "class_name": "Pitting",
      "conf": 0.8414351940155029,
      "x1": 382.9842834472656,
      "y1": 227.9610595703125,
      "x2": 530.0650634765625,
      "y2": 429.09735107421875
    },
    {
      "image_name": "test_264.jpg",
      "class_id": 4,
      "class_name": "Pitting",
      "conf": 0.7652426362037659,
      "x1": 218.71058654785156,
      "y1": 496.41632080078125,
      "x2": 427.4920349121094,
      "y2": 639.0
    },
    {
      "image_name": "test_265.jpg",
      "class_id": 4,
      "class_name": "Pitting",
      "conf": 0.8380180597305298,
      "x1": 221.0757598876953,
      "y1": 75.27168273925781,
      "x2": 422.0,
      "y2": 241.41395568847656
    },
    {
      "image_name": "test_266.jpg",
      "class_id": 1,
      "class_name": "Cracks",
      "conf": 0.8807970285415649,
      "x1": 19.133514404296875,
      "y1": 0.0,
      "x2": 377.07275390625,
      "y2": 219.63571166992188
    },
    {
      "image_name": "test_267.jpg",
      "class_id": 3,
      "class_name": "Scratches",
      "conf": 0.8626990914344788,
      "x1": 374.439453125,
      "y1": 372.0634460449219,
      "x2": 459.4062194824219,
      "y2": 558.6644287109375
    },
    {
      "image_name": "test_267.jpg",
      "class_id": 1,
      "class_name": "Cracks",
      "conf": 0.5570924878120422,
      "x1": 446.58489990234375,
      "y1": 0.14228248596191406,
      "x2": 631.00732421875,
      "y2": 53.901878356933594
    },
    {
      "image_name": "test_268.jpg",
      "class_id": 3,
      "class_name": "Scratches",
      "conf": 0.8692712783813477,
      "x1": 254.0776824951172,
      "y1": 0.0,
      "x2": 404.4388122558594,
      "y2": 125.9671401977539
    },
    {
      "image_name": "test_269.jpg",
      "class_id": 3,
      "class_name": "Scratches",
      "conf": 0.6587468981742859,
      "x1": 1.0994367599487305,
      "y1": 251.73130798339844,
      "x2": 46.13577651977539,
      "y2": 603.1030883789062
    },
    {
      "image_name": "test_27.jpg",
      "class_id": 1,
      "class_name": "Cracks",
      "conf": 0.6641048192977905,
      "x1": 0.0,
      "y1": 2.2673110961914062,
      "x2": 340.555419921875,
      "y2": 203.67396545410156
    },
    {
      "image_name": "test_270.jpg",
      "class_id": 3,
      "class_name": "Scratches",
      "conf": 0.8358858227729797,
      "x1": 3.3304824829101562,
      "y1": 289.609130859375,
      "x2": 102.18411254882812,
      "y2": 639.0
    },
    {
      "image_name": "test_271.jpg",
      "class_id": 3,
      "class_name": "Scratches",
      "conf": 0.704871654510498,
      "x1": 360.67919921875,
      "y1": 276.57977294921875,
      "x2": 435.7868347167969,
      "y2": 629.5220947265625
    },
    {
      "image_name": "test_272.jpg",
      "class_id": 3,
      "class_name": "Scratches",
      "conf": 0.6788594722747803,
      "x1": 454.824951171875,
      "y1": 245.67755126953125,
      "x2": 523.5689697265625,
      "y2": 599.0543212890625
    },
    {
      "image_name": "test_273.jpg",
      "class_id": 3,
      "class_name": "Scratches",
      "conf": 0.5385282039642334,
      "x1": 320.8310241699219,
      "y1": 0.0,
      "x2": 424.7107849121094,
      "y2": 147.6765899658203
    },
    {
      "image_name": "test_274.jpg",
      "class_id": 3,
      "class_name": "Scratches",
      "conf": 0.8584814667701721,
      "x1": 474.27239990234375,
      "y1": 290.8133544921875,
      "x2": 582.6068725585938,
      "y2": 639.0
    },
    {
      "image_name": "test_274.jpg",
      "class_id": 3,
      "class_name": "Scratches",
      "conf": 0.8333246111869812,
      "x1": 353.3866882324219,
      "y1": 0.0,
      "x2": 433.2996826171875,
      "y2": 250.7975311279297
    },
    {
      "image_name": "test_275.jpg",
      "class_id": 3,
      "class_name": "Scratches",
      "conf": 0.8584814667701721,
      "x1": 474.27239990234375,
      "y1": 290.8133544921875,
      "x2": 582.6068725585938,
      "y2": 639.0
    },
    {
      "image_name": "test_275.jpg",
      "class_id": 3,
      "class_name": "Scratches",
      "conf": 0.8333246111869812,
      "x1": 353.3866882324219,
      "y1": 0.0,
      "x2": 433.2996826171875,
      "y2": 250.7975311279297
    },
    {
      "image_name": "test_276.jpg",
      "class_id": 3,
      "class_name": "Scratches",
      "conf": 0.9039745330810547,
      "x1": 1.78631591796875,
      "y1": 521.8383178710938,
      "x2": 268.0323486328125,
      "y2": 639.0
    },
    {
      "image_name": "test_276.jpg",
      "class_id": 3,
      "class_name": "Scratches",
      "conf": 0.8921873569488525,
      "x1": 69.47016906738281,
      "y1": 131.57778930664062,
      "x2": 318.8645324707031,
      "y2": 297.1896667480469
    },
    {
      "image_name": "test_277.jpg",
      "class_id": 1,
      "class_name": "Cracks",
      "conf": 0.7779753804206848,
      "x1": 0.6414222717285156,
      "y1": 187.3795623779297,
      "x2": 77.73906707763672,
      "y2": 352.62469482421875
    },
    {
      "image_name": "test_278.jpg",
      "class_id": 3,
      "class_name": "Scratches",
      "conf": 0.8718026280403137,
      "x1": 0.0,
      "y1": 343.2598876953125,
      "x2": 278.74957275390625,
      "y2": 398.5442810058594
    },
    {
      "image_name": "test_279.jpg",
      "class_id": 3,
      "class_name": "Scratches",
      "conf": 0.8964328765869141,
      "x1": 0.912811279296875,
      "y1": 40.19261169433594,
      "x2": 269.28839111328125,
      "y2": 258.1419372558594
    },
    {
      "image_name": "test_28.jpg",
      "class_id": 1,
      "class_name": "Cracks",
      "conf": 0.8677098155021667,
      "x1": 302.0968017578125,
      "y1": 408.8284606933594,
      "x2": 458.54473876953125,
      "y2": 516.1883544921875
    },
    {
      "image_name": "test_28.jpg",
      "class_id": 1,
      "class_name": "Cracks",
      "conf": 0.8589553833007812,
      "x1": 342.60552978515625,
      "y1": 544.2333984375,
      "x2": 499.45330810546875,
      "y2": 639.0
    },
    {
      "image_name": "test_280.jpg",
      "class_id": 3,
      "class_name": "Scratches",
      "conf": 0.8899121284484863,
      "x1": 550.6194458007812,
      "y1": 130.27706909179688,
      "x2": 639.0,
      "y2": 301.29766845703125
    },
    {
      "image_name": "test_280.jpg",
      "class_id": 3,
      "class_name": "Scratches",
      "conf": 0.8451772928237915,
      "x1": 418.5722351074219,
      "y1": 526.443603515625,
      "x2": 639.0,
      "y2": 639.0
    },
    {
      "image_name": "test_281.jpg",
      "class_id": 1,
      "class_name": "Cracks",
      "conf": 0.9038048982620239,
      "x1": 242.0796356201172,
      "y1": 197.22146606445312,
      "x2": 562.6869506835938,
      "y2": 360.89886474609375
    },
    {
      "image_name": "test_282.jpg",
      "class_id": 3,
      "class_name": "Scratches",
      "conf": 0.9019206762313843,
      "x1": 170.4232177734375,
      "y1": 145.80136108398438,
      "x2": 361.8872985839844,
      "y2": 330.4093322753906
    },
    {
      "image_name": "test_282.jpg",
      "class_id": 3,
      "class_name": "Scratches",
      "conf": 0.8543993234634399,
      "x1": 394.74005126953125,
      "y1": 341.02630615234375,
      "x2": 639.0,
      "y2": 402.548828125
    },
    {
      "image_name": "test_282.jpg",
      "class_id": 3,
      "class_name": "Scratches",
      "conf": 0.7602949142456055,
      "x1": 178.032958984375,
      "y1": 346.943115234375,
      "x2": 302.3406066894531,
      "y2": 415.6758728027344
    },
    {
      "image_name": "test_283.jpg",
      "class_id": 3,
      "class_name": "Scratches",
      "conf": 0.9019206762313843,
      "x1": 170.4232177734375,
      "y1": 145.80136108398438,
      "x2": 361.8872985839844,
      "y2": 330.4093322753906
    },
    {
      "image_name": "test_283.jpg",
      "class_id": 3,
      "class_name": "Scratches",
      "conf": 0.8543993234634399,
      "x1": 394.74005126953125,
      "y1": 341.02630615234375,
      "x2": 639.0,
      "y2": 402.548828125
    },
    {
      "image_name": "test_283.jpg",
      "class_id": 3,
      "class_name": "Scratches",
      "conf": 0.7602949142456055,
      "x1": 178.032958984375,
      "y1": 346.943115234375,
      "x2": 302.3406066894531,
      "y2": 415.6758728027344
    },
    {
      "image_name": "test_284.jpg",
      "class_id": 3,
      "class_name": "Scratches",
      "conf": 0.8687154054641724,
      "x1": 216.3402557373047,
      "y1": 27.92373275756836,
      "x2": 455.7150573730469,
      "y2": 261.4508972167969
    },
    {
      "image_name": "test_284.jpg",
      "class_id": 3,
      "class_name": "Scratches",
      "conf": 0.76082843542099,
      "x1": 221.84579467773438,
      "y1": 276.6209716796875,
      "x2": 376.85992431640625,
      "y2": 362.97296142578125
    },
    {
      "image_name": "test_285.jpg",
      "class_id": 3,
      "class_name": "Scratches",
      "conf": 0.9318356513977051,
      "x1": 423.5815734863281,
      "y1": 52.27165985107422,
      "x2": 639.0,
      "y2": 262.1298522949219
    },
    {
      "image_name": "test_285.jpg",
      "class_id": 3,
      "class_name": "Scratches",
      "conf": 0.4052722156047821,
      "x1": 3.6785202026367188,
      "y1": 31.1131591796875,
      "x2": 85.05825805664062,
      "y2": 639.0
    },
    {
      "image_name": "test_286.jpg",
      "class_id": 2,
      "class_name": "patches",
      "conf": 0.6411977410316467,
      "x1": 8.840744018554688,
      "y1": 223.52633666992188,
      "x2": 280.38262939453125,
      "y2": 412.9349060058594
    },
    {
      "image_name": "test_287.jpg",
      "class_id": 2,
      "class_name": "patches",
      "conf": 0.7245780229568481,
      "x1": 2.6133575439453125,
      "y1": 216.8663330078125,
      "x2": 355.7968444824219,
      "y2": 464.4429016113281
    },
    {
      "image_name": "test_287.jpg",
      "class_id": 0,
      "class_name": "Rust",
      "conf": 0.548401415348053,
      "x1": 0.0,
      "y1": 214.78347778320312,
      "x2": 345.721923828125,
      "y2": 471.61212158203125
    },
    {
      "image_name": "test_289.jpg",
      "class_id": 0,
      "class_name": "Rust",
      "conf": 0.8097277879714966,
      "x1": 4.4771881103515625,
      "y1": 247.24989318847656,
      "x2": 638.7332763671875,
      "y2": 511.359130859375
    },
    {
      "image_name": "test_289.jpg",
      "class_id": 2,
      "class_name": "patches",
      "conf": 0.6389479041099548,
      "x1": 316.6550598144531,
      "y1": 246.4403076171875,
      "x2": 639.0,
      "y2": 435.4134521484375
    },
    {
      "image_name": "test_29.jpg",
      "class_id": 1,
      "class_name": "Cracks",
      "conf": 0.8708171844482422,
      "x1": 338.34954833984375,
      "y1": 380.87200927734375,
      "x2": 501.2017822265625,
      "y2": 584.1320190429688
    },
    {
      "image_name": "test_29.jpg",
      "class_id": 1,
      "class_name": "Cracks",
      "conf": 0.8673731684684753,
      "x1": 301.81793212890625,
      "y1": 249.1514434814453,
      "x2": 458.2724304199219,
      "y2": 355.8636169433594
    },
    {
      "image_name": "test_291.jpg",
      "class_id": 1,
      "class_name": "Cracks",
      "conf": 0.6835251450538635,
      "x1": 6.6442108154296875,
      "y1": 268.1211853027344,
      "x2": 439.1669921875,
      "y2": 639.0
    },
    {
      "image_name": "test_291.jpg",
      "class_id": 1,
      "class_name": "Cracks",
      "conf": 0.6369178891181946,
      "x1": 472.3016357421875,
      "y1": 257.1896667480469,
      "x2": 636.4019165039062,
      "y2": 486.55377197265625
    },
    {
      "image_name": "test_292.jpg",
      "class_id": 1,
      "class_name": "Cracks",
      "conf": 0.8178656101226807,
      "x1": 385.5530090332031,
      "y1": 60.00909423828125,
      "x2": 639.0,
      "y2": 356.6827392578125
    },
    {
      "image_name": "test_293.jpg",
      "class_id": 1,
      "class_name": "Cracks",
      "conf": 0.7687332034111023,
      "x1": 360.4613952636719,
      "y1": 360.0727233886719,
      "x2": 637.0059814453125,
      "y2": 639.0
    },
    {
      "image_name": "test_293.jpg",
      "class_id": 1,
      "class_name": "Cracks",
      "conf": 0.37421879172325134,
      "x1": 18.83507537841797,
      "y1": 0.966827392578125,
      "x2": 259.6237487792969,
      "y2": 189.06057739257812
    },
    {
      "image_name": "test_294.jpg",
      "class_id": 1,
      "class_name": "Cracks",
      "conf": 0.6171665787696838,
      "x1": 303.126953125,
      "y1": 257.7008056640625,
      "x2": 475.836669921875,
      "y2": 483.97894287109375
    },
    {
      "image_name": "test_295.jpg",
      "class_id": 1,
      "class_name": "Cracks",
      "conf": 0.7880942821502686,
      "x1": 229.0908203125,
      "y1": 56.378631591796875,
      "x2": 476.044677734375,
      "y2": 355.93865966796875
    },
    {
      "image_name": "test_296.jpg",
      "class_id": 1,
      "class_name": "Cracks",
      "conf": 0.7900447249412537,
      "x1": 201.12974548339844,
      "y1": 355.9243469238281,
      "x2": 478.9014587402344,
      "y2": 639.0
    },
    {
      "image_name": "test_298.jpg",
      "class_id": 3,
      "class_name": "Scratches",
      "conf": 0.8461968302726746,
      "x1": 218.91690063476562,
      "y1": 313.493408203125,
      "x2": 333.6146240234375,
      "y2": 639.0
    },
    {
      "image_name": "test_299.jpg",
      "class_id": 3,
      "class_name": "Scratches",
      "conf": 0.7747538685798645,
      "x1": 217.49398803710938,
      "y1": 0.0,
      "x2": 341.09674072265625,
      "y2": 310.3797607421875
    },
    {
      "image_name": "test_3.jpg",
      "class_id": 4,
      "class_name": "Pitting",
      "conf": 0.8840392827987671,
      "x1": 0.0,
      "y1": 231.03073120117188,
      "x2": 216.57070922851562,
      "y2": 409.347412109375
    },
    {
      "image_name": "test_30.jpg",
      "class_id": 1,
      "class_name": "Cracks",
      "conf": 0.8708171844482422,
      "x1": 338.34954833984375,
      "y1": 380.87200927734375,
      "x2": 501.2017822265625,
      "y2": 584.1320190429688
    },
    {
      "image_name": "test_30.jpg",
      "class_id": 1,
      "class_name": "Cracks",
      "conf": 0.8673731684684753,
      "x1": 301.81793212890625,
      "y1": 249.1514434814453,
      "x2": 458.2724304199219,
      "y2": 355.8636169433594
    },
    {
      "image_name": "test_300.jpg",
      "class_id": 3,
      "class_name": "Scratches",
      "conf": 0.839602530002594,
      "x1": 152.68817138671875,
      "y1": 312.6759033203125,
      "x2": 266.61090087890625,
      "y2": 639.0
    },
    {
      "image_name": "test_301.jpg",
      "class_id": 3,
      "class_name": "Scratches",
      "conf": 0.7721872329711914,
      "x1": 156.9391632080078,
      "y1": 0.0,
      "x2": 269.1579895019531,
      "y2": 309.86260986328125
    },
    {
      "image_name": "test_302.jpg",
      "class_id": 3,
      "class_name": "Scratches",
      "conf": 0.8780007362365723,
      "x1": 215.25613403320312,
      "y1": 472.4811096191406,
      "x2": 352.94561767578125,
      "y2": 639.0
    },
    {
      "image_name": "test_303.jpg",
      "class_id": 3,
      "class_name": "Scratches",
      "conf": 0.8470844030380249,
      "x1": 217.62759399414062,
      "y1": 0.0,
      "x2": 348.3971252441406,
      "y2": 231.60037231445312
    },
    {
      "image_name": "test_306.jpg",
      "class_id": 4,
      "class_name": "Pitting",
      "conf": 0.8807970285415649,
      "x1": 205.56015014648438,
      "y1": 204.51400756835938,
      "x2": 427.6594543457031,
      "y2": 423.14013671875
    },
    {
      "image_name": "test_307.jpg",
      "class_id": 4,
      "class_name": "Pitting",
      "conf": 0.9000037312507629,
      "x1": 217.34573364257812,
      "y1": 220.03070068359375,
      "x2": 425.2606201171875,
      "y2": 419.2624206542969
    },
    {
      "image_name": "test_308.jpg",
      "class_id": 4,
      "class_name": "Pitting",
      "conf": 0.91804039478302,
      "x1": 227.27032470703125,
      "y1": 215.07015991210938,
      "x2": 411.6124267578125,
      "y2": 432.9796142578125
    },
    {
      "image_name": "test_309.jpg",
      "class_id": 4,
      "class_name": "Pitting",
      "conf": 0.8728901743888855,
      "x1": 220.52134704589844,
      "y1": 226.03468322753906,
      "x2": 423.7425842285156,
      "y2": 419.84173583984375
    },
    {
      "image_name": "test_31.jpg",
      "class_id": 1,
      "class_name": "Cracks",
      "conf": 0.875361442565918,
      "x1": 0.0,
      "y1": 389.6154479980469,
      "x2": 140.19683837890625,
      "y2": 549.5872192382812
    },
    {
      "image_name": "test_310.jpg",
      "class_id": 4,
      "class_name": "Pitting",
      "conf": 0.8727816939353943,
      "x1": 440.4789733886719,
      "y1": 517.3667602539062,
      "x2": 634.39794921875,
      "y2": 639.0
    },
    {
      "image_name": "test_310.jpg",
      "class_id": 4,
      "class_name": "Pitting",
      "conf": 0.8632764220237732,
      "x1": 222.84771728515625,
      "y1": 217.12405395507812,
      "x2": 409.64862060546875,
      "y2": 422.54443359375
    },
    {
      "image_name": "test_311.jpg",
      "class_id": 4,
      "class_name": "Pitting",
      "conf": 0.5044859647750854,
      "x1": 204.29156494140625,
      "y1": 0.0057888031005859375,
      "x2": 434.20257568359375,
      "y2": 54.226070404052734
    },
    {
      "image_name": "test_312.jpg",
      "class_id": 4,
      "class_name": "Pitting",
      "conf": 0.8728901743888855,
      "x1": 220.52134704589844,
      "y1": 226.03468322753906,
      "x2": 423.7425842285156,
      "y2": 419.84173583984375
    },
    {
      "image_name": "test_313.jpg",
      "class_id": 4,
      "class_name": "Pitting",
      "conf": 0.8727816939353943,
      "x1": 440.4789733886719,
      "y1": 517.3667602539062,
      "x2": 634.39794921875,
      "y2": 639.0
    },
    {
      "image_name": "test_313.jpg",
      "class_id": 4,
      "class_name": "Pitting",
      "conf": 0.8632764220237732,
      "x1": 222.84771728515625,
      "y1": 217.12405395507812,
      "x2": 409.64862060546875,
      "y2": 422.54443359375
    },
    {
      "image_name": "test_314.jpg",
      "class_id": 4,
      "class_name": "Pitting",
      "conf": 0.8543993234634399,
      "x1": 239.005126953125,
      "y1": 216.89013671875,
      "x2": 409.813232421875,
      "y2": 432.88873291015625
    },
    {
      "image_name": "test_315.jpg",
      "class_id": 4,
      "class_name": "Pitting",
      "conf": 0.8389438390731812,
      "x1": 231.66415405273438,
      "y1": 2.0901412963867188,
      "x2": 410.7740478515625,
      "y2": 222.26101684570312
    },
    {
      "image_name": "test_316.jpg",
      "class_id": 4,
      "class_name": "Pitting",
      "conf": 0.8389438390731812,
      "x1": 267.6877136230469,
      "y1": 530.7027587890625,
      "x2": 497.93658447265625,
      "y2": 639.0
    },
    {
      "image_name": "test_317.jpg",
      "class_id": 4,
      "class_name": "Pitting",
      "conf": 0.8822250962257385,
      "x1": 267.9670104980469,
      "y1": 48.05802917480469,
      "x2": 494.9727783203125,
      "y2": 343.47418212890625
    },
    {
      "image_name": "test_318.jpg",
      "class_id": 2,
      "class_name": "patches",
      "conf": 0.7796576023101807,
      "x1": 569.2191772460938,
      "y1": 497.00439453125,
      "x2": 639.0,
      "y2": 639.0
    },
    {
      "image_name": "test_319.jpg",
      "class_id": 2,
      "class_name": "patches",
      "conf": 0.8584814667701721,
      "x1": 567.855712890625,
      "y1": 21.108596801757812,
      "x2": 639.0,
      "y2": 265.7112121582031
    },
    {
      "image_name": "test_32.jpg",
      "class_id": 1,
      "class_name": "Cracks",
      "conf": 0.8842393159866333,
      "x1": 0.0,
      "y1": 230.6322021484375,
      "x2": 140.8714599609375,
      "y2": 389.1255798339844
    },
    {
      "image_name": "test_320.jpg",
      "class_id": 2,
      "class_name": "patches",
      "conf": 0.8748277425765991,
      "x1": 90.47853088378906,
      "y1": 520.7386474609375,
      "x2": 203.01950073242188,
      "y2": 639.0
    },
    {
      "image_name": "test_321.jpg",
      "class_id": 2,
      "class_name": "patches",
      "conf": 0.9135223627090454,
      "x1": 87.70572662353516,
      "y1": 40.82658386230469,
      "x2": 202.43455505371094,
      "y2": 264.34832763671875
    },
    {
      "image_name": "test_322.jpg",
      "class_id": 1,
      "class_name": "Cracks",
      "conf": 0.8432507514953613,
      "x1": 0.0,
      "y1": 284.7438659667969,
      "x2": 639.0,
      "y2": 639.0
    },
    {
      "image_name": "test_323.jpg",
      "class_id": 1,
      "class_name": "Cracks",
      "conf": 0.7932661771774292,
      "x1": 0.0,
      "y1": 0.0,
      "x2": 636.175048828125,
      "y2": 431.4879150390625
    },
    {
      "image_name": "test_324.jpg",
      "class_id": 1,
      "class_name": "Cracks",
      "conf": 0.6599532961845398,
      "x1": 322.3731689453125,
      "y1": 266.8421630859375,
      "x2": 639.0,
      "y2": 639.0
    },
    {
      "image_name": "test_325.jpg",
      "class_id": 1,
      "class_name": "Cracks",
      "conf": 0.5749915242195129,
      "x1": 78.07327270507812,
      "y1": 0.0,
      "x2": 564.6522216796875,
      "y2": 569.2890625
    },
    {
      "image_name": "test_326.jpg",
      "class_id": 1,
      "class_name": "Cracks",
      "conf": 0.8791467547416687,
      "x1": 295.6280517578125,
      "y1": 337.074462890625,
      "x2": 613.1616821289062,
      "y2": 638.524658203125
    },
    {
      "image_name": "test_326.jpg",
      "class_id": 1,
      "class_name": "Cracks",
      "conf": 0.5305253267288208,
      "x1": 0.0,
      "y1": 318.662109375,
      "x2": 277.51171875,
      "y2": 639.0
    },
    {
      "image_name": "test_327.jpg",
      "class_id": 1,
      "class_name": "Cracks",
      "conf": 0.8766343593597412,
      "x1": 232.6961669921875,
      "y1": 335.517578125,
      "x2": 546.5919189453125,
      "y2": 638.9544067382812
    },
    {
      "image_name": "test_327.jpg",
      "class_id": 1,
      "class_name": "Cracks",
      "conf": 0.44504714012145996,
      "x1": 0.0,
      "y1": 266.3559265136719,
      "x2": 164.5042724609375,
      "y2": 639.0
    },
    {
      "image_name": "test_328.jpg",
      "class_id": 1,
      "class_name": "Cracks",
      "conf": 0.8559715747833252,
      "x1": 4.5914306640625,
      "y1": 58.05192565917969,
      "x2": 358.3585205078125,
      "y2": 299.0411376953125
    },
    {
      "image_name": "test_328.jpg",
      "class_id": 1,
      "class_name": "Cracks",
      "conf": 0.3944341838359833,
      "x1": 512.531005859375,
      "y1": 198.1707000732422,
      "x2": 639.0,
      "y2": 488.0223083496094
    },
    {
      "image_name": "test_329.jpg",
      "class_id": 1,
      "class_name": "Cracks",
      "conf": 0.8178656101226807,
      "x1": 3.148345947265625,
      "y1": 540.0485229492188,
      "x2": 335.85540771484375,
      "y2": 639.0
    },
    {
      "image_name": "test_33.jpg",
      "class_id": 1,
      "class_name": "Cracks",
      "conf": 0.8804891109466553,
      "x1": 176.48629760742188,
      "y1": 399.412353515625,
      "x2": 442.5794982910156,
      "y2": 552.2044067382812
    },
    {
      "image_name": "test_330.jpg",
      "class_id": 1,
      "class_name": "Cracks",
      "conf": 0.8621196746826172,
      "x1": 0.527496337890625,
      "y1": 211.59567260742188,
      "x2": 344.71875,
      "y2": 487.41741943359375
    },
    {
      "image_name": "test_331.jpg",
      "class_id": 1,
      "class_name": "Cracks",
      "conf": 0.7862948179244995,
      "x1": 0.0,
      "y1": 214.3679656982422,
      "x2": 279.5711669921875,
      "y2": 487.9082336425781
    },
    {
      "image_name": "test_332.jpg",
      "class_id": 1,
      "class_name": "Cracks",
      "conf": 0.8772666454315186,
      "x1": 353.0523681640625,
      "y1": 211.10009765625,
      "x2": 639.0,
      "y2": 476.3280334472656
    },
    {
      "image_name": "test_333.jpg",
      "class_id": 2,
      "class_name": "patches",
      "conf": 0.8949732184410095,
      "x1": 237.32598876953125,
      "y1": 522.5424194335938,
      "x2": 353.2517395019531,
      "y2": 639.0
    },
    {
      "image_name": "test_334.jpg",
      "class_id": 2,
      "class_name": "patches",
      "conf": 0.9029524326324463,
      "x1": 238.77565002441406,
      "y1": 43.363739013671875,
      "x2": 354.5141906738281,
      "y2": 163.3801727294922
    },
    {
      "image_name": "test_335.jpg",
      "class_id": 1,
      "class_name": "Cracks",
      "conf": 0.8079156875610352,
      "x1": 167.9595947265625,
      "y1": 258.989501953125,
      "x2": 322.8005676269531,
      "y2": 628.177001953125
    },
    {
      "image_name": "test_336.jpg",
      "class_id": 1,
      "class_name": "Cracks",
      "conf": 0.8070047497749329,
      "x1": 158.12889099121094,
      "y1": 0.0,
      "x2": 314.13470458984375,
      "y2": 290.46014404296875
    },
    {
      "image_name": "test_337.jpg",
      "class_id": 1,
      "class_name": "Cracks",
      "conf": 0.8333246111869812,
      "x1": 101.91712951660156,
      "y1": 252.1753387451172,
      "x2": 259.12884521484375,
      "y2": 629.5596923828125
    },
    {
      "image_name": "test_338.jpg",
      "class_id": 1,
      "class_name": "Cracks",
      "conf": 0.8028648495674133,
      "x1": 93.92024230957031,
      "y1": 0.0,
      "x2": 251.661376953125,
      "y2": 293.2060241699219
    },
    {
      "image_name": "test_339.jpg",
      "class_id": 1,
      "class_name": "Cracks",
      "conf": 0.7903685569763184,
      "x1": 166.77833557128906,
      "y1": 256.747802734375,
      "x2": 338.0882568359375,
      "y2": 638.70556640625
    },
    {
      "image_name": "test_34.jpg",
      "class_id": 1,
      "class_name": "Cracks",
      "conf": 0.8860265612602234,
      "x1": 176.96109008789062,
      "y1": 239.6285858154297,
      "x2": 443.1883544921875,
      "y2": 393.2998046875
    },
    {
      "image_name": "test_340.jpg",
      "class_id": 1,
      "class_name": "Cracks",
      "conf": 0.7757747173309326,
      "x1": 142.5029296875,
      "y1": 0.422698974609375,
      "x2": 316.5616455078125,
      "y2": 292.07763671875
    },
    {
      "image_name": "test_341.jpg",
      "class_id": 1,
      "class_name": "Cracks",
      "conf": 0.815232515335083,
      "x1": 99.85299682617188,
      "y1": 257.47613525390625,
      "x2": 272.58233642578125,
      "y2": 637.0311889648438
    },
    {
      "image_name": "test_342.jpg",
      "class_id": 1,
      "class_name": "Cracks",
      "conf": 0.775604784488678,
      "x1": 86.34954071044922,
      "y1": 0.9318695068359375,
      "x2": 253.14706420898438,
      "y2": 296.9084777832031
    },
    {
      "image_name": "test_343.jpg",
      "class_id": 1,
      "class_name": "Cracks",
      "conf": 0.780829668045044,
      "x1": 577.9313354492188,
      "y1": 272.82550048828125,
      "x2": 639.0,
      "y2": 639.0
    },
    {
      "image_name": "test_344.jpg",
      "class_id": 1,
      "class_name": "Cracks",
      "conf": 0.8414351940155029,
      "x1": 232.22442626953125,
      "y1": 511.1932373046875,
      "x2": 360.2454833984375,
      "y2": 639.0
    },
    {
      "image_name": "test_345.jpg",
      "class_id": 1,
      "class_name": "Cracks",
      "conf": 0.8103289008140564,
      "x1": 249.25091552734375,
      "y1": 327.18426513671875,
      "x2": 361.69940185546875,
      "y2": 635.1264038085938
    },
    {
      "image_name": "test_346.jpg",
      "class_id": 1,
      "class_name": "Cracks",
      "conf": 0.8587185740470886,
      "x1": 174.40838623046875,
      "y1": 509.8081970214844,
      "x2": 294.76177978515625,
      "y2": 639.0
    },
    {
      "image_name": "test_347.jpg",
      "class_id": 1,
      "class_name": "Cracks",
      "conf": 0.8039445281028748,
      "x1": 185.52638244628906,
      "y1": 326.8996887207031,
      "x2": 296.79913330078125,
      "y2": 635.6498413085938
    },
    {
      "image_name": "test_348.jpg",
      "class_id": 4,
      "class_name": "Pitting",
      "conf": 0.8060905337333679,
      "x1": 214.25877380371094,
      "y1": 481.1391296386719,
      "x2": 284.7512512207031,
      "y2": 639.0
    },
    {
      "image_name": "test_349.jpg",
      "class_id": 1,
      "class_name": "Cracks",
      "conf": 0.8707072734832764,
      "x1": 101.57865905761719,
      "y1": 281.4022216796875,
      "x2": 180.20443725585938,
      "y2": 639.0
    },
    {
      "image_name": "test_349.jpg",
      "class_id": 4,
      "class_name": "Pitting",
      "conf": 0.8019358515739441,
      "x1": 172.95672607421875,
      "y1": 32.097412109375,
      "x2": 230.84117126464844,
      "y2": 177.88836669921875
    },
    {
      "image_name": "test_35.jpg",
      "class_id": 4,
      "class_name": "Pitting",
      "conf": 0.6959583163261414,
      "x1": 254.7741241455078,
      "y1": 257.26934814453125,
      "x2": 394.8817138671875,
      "y2": 379.06512451171875
    },
    {
      "image_name": "test_350.jpg",
      "class_id": 1,
      "class_name": "Cracks",
      "conf": 0.873214840888977,
      "x1": 121.10481262207031,
      "y1": 317.6690673828125,
      "x2": 222.53213500976562,
      "y2": 639.0
    },
    {
      "image_name": "test_350.jpg",
      "class_id": 4,
      "class_name": "Pitting",
      "conf": 0.8231863379478455,
      "x1": 206.65313720703125,
      "y1": 33.131309509277344,
      "x2": 274.2767639160156,
      "y2": 211.1663055419922
    },
    {
      "image_name": "test_36.jpg",
      "class_id": 2,
      "class_name": "patches",
      "conf": 0.872347354888916,
      "x1": 262.1054992675781,
      "y1": 248.55101013183594,
      "x2": 371.74078369140625,
      "y2": 393.5719909667969
    },
    {
      "image_name": "test_37.jpg",
      "class_id": 2,
      "class_name": "patches",
      "conf": 0.8992984294891357,
      "x1": 250.10455322265625,
      "y1": 277.2265625,
      "x2": 389.0168762207031,
      "y2": 360.4774475097656
    },
    {
      "image_name": "test_38.jpg",
      "class_id": 2,
      "class_name": "patches",
      "conf": 0.8397339582443237,
      "x1": 237.83547973632812,
      "y1": 0.0,
      "x2": 386.1025390625,
      "y2": 121.93037414550781
    },
    {
      "image_name": "test_39.jpg",
      "class_id": 4,
      "class_name": "Pitting",
      "conf": 0.6933691501617432,
      "x1": 521.2257080078125,
      "y1": 255.65603637695312,
      "x2": 639.0,
      "y2": 376.027099609375
    },
    {
      "image_name": "test_4.jpg",
      "class_id": 2,
      "class_name": "patches",
      "conf": 0.9293122291564941,
      "x1": 109.68177795410156,
      "y1": 113.55807495117188,
      "x2": 235.67222595214844,
      "y2": 250.1245574951172
    },
    {
      "image_name": "test_40.jpg",
      "class_id": 0,
      "class_name": "Rust",
      "conf": 0.8244618773460388,
      "x1": 287.9089660644531,
      "y1": 393.2403564453125,
      "x2": 348.350341796875,
      "y2": 514.3916625976562
    },
    {
      "image_name": "test_41.jpg",
      "class_id": 0,
      "class_name": "Rust",
      "conf": 0.7590468525886536,
      "x1": 287.5076599121094,
      "y1": 103.12347412109375,
      "x2": 350.06219482421875,
      "y2": 221.05532836914062
    },
    {
      "image_name": "test_45.jpg",
      "class_id": 0,
      "class_name": "Rust",
      "conf": 0.9267027974128723,
      "x1": 277.8878479003906,
      "y1": 237.36471557617188,
      "x2": 361.32684326171875,
      "y2": 399.01165771484375
    },
    {
      "image_name": "test_46.jpg",
      "class_id": 0,
      "class_name": "Rust",
      "conf": 0.9156582355499268,
      "x1": 292.9607238769531,
      "y1": 60.09629440307617,
      "x2": 349.07257080078125,
      "y2": 166.5154266357422
    },
    {
      "image_name": "test_46.jpg",
      "class_id": 0,
      "class_name": "Rust",
      "conf": 0.902265727519989,
      "x1": 279.6539306640625,
      "y1": 507.32318115234375,
      "x2": 358.88909912109375,
      "y2": 638.9053955078125
    },
    {
      "image_name": "test_47.jpg",
      "class_id": 0,
      "class_name": "Rust",
      "conf": 0.9119669198989868,
      "x1": 284.33441162109375,
      "y1": 254.15411376953125,
      "x2": 357.2955322265625,
      "y2": 386.8135681152344
    },
    {
      "image_name": "test_48.jpg",
      "class_id": 0,
      "class_name": "Rust",
      "conf": 0.9244152307510376,
      "x1": 277.2703552246094,
      "y1": 237.005859375,
      "x2": 361.11993408203125,
      "y2": 398.8204345703125
    },
    {
      "image_name": "test_49.jpg",
      "class_id": 0,
      "class_name": "Rust",
      "conf": 0.9100669622421265,
      "x1": 295.2876892089844,
      "y1": 60.17920684814453,
      "x2": 349.1271057128906,
      "y2": 167.70755004882812
    },
    {
      "image_name": "test_49.jpg",
      "class_id": 0,
      "class_name": "Rust",
      "conf": 0.9003546833992004,
      "x1": 280.6322937011719,
      "y1": 506.9212951660156,
      "x2": 360.8187561035156,
      "y2": 638.730224609375
    },
    {
      "image_name": "test_5.jpg",
      "class_id": 2,
      "class_name": "patches",
      "conf": 0.9293122291564941,
      "x1": 109.68177795410156,
      "y1": 113.55807495117188,
      "x2": 235.67222595214844,
      "y2": 250.1245574951172
    },
    {
      "image_name": "test_50.jpg",
      "class_id": 0,
      "class_name": "Rust",
      "conf": 0.9102267622947693,
      "x1": 284.78363037109375,
      "y1": 253.62481689453125,
      "x2": 357.4266357421875,
      "y2": 386.976318359375
    },
    {
      "image_name": "test_51.jpg",
      "class_id": 0,
      "class_name": "Rust",
      "conf": 0.7631309032440186,
      "x1": 232.85147094726562,
      "y1": 298.0748291015625,
      "x2": 408.2669982910156,
      "y2": 354.15423583984375
    },
    {
      "image_name": "test_52.jpg",
      "class_id": 0,
      "class_name": "Rust",
      "conf": 0.6893056035041809,
      "x1": 229.77479553222656,
      "y1": 298.4632568359375,
      "x2": 405.3280029296875,
      "y2": 353.648681640625
    },
    {
      "image_name": "test_53.jpg",
      "class_id": 0,
      "class_name": "Rust",
      "conf": 0.8856314420700073,
      "x1": 285.65350341796875,
      "y1": 217.6149139404297,
      "x2": 375.5834655761719,
      "y2": 465.017333984375
    },
    {
      "image_name": "test_56.jpg",
      "class_id": 0,
      "class_name": "Rust",
      "conf": 0.8267117738723755,
      "x1": 283.03350830078125,
      "y1": 25.19198226928711,
      "x2": 378.6599426269531,
      "y2": 166.9755859375
    },
    {
      "image_name": "test_57.jpg",
      "class_id": 0,
      "class_name": "Rust",
      "conf": 0.8927496671676636,
      "x1": 220.03912353515625,
      "y1": 215.7472686767578,
      "x2": 308.19696044921875,
      "y2": 464.8363037109375
    },
    {
      "image_name": "test_59.jpg",
      "class_id": 4,
      "class_name": "Pitting",
      "conf": 0.447973370552063,
      "x1": 330.5638427734375,
      "y1": 498.2991638183594,
      "x2": 478.6466979980469,
      "y2": 639.0
    },
    {
      "image_name": "test_6.jpg",
      "class_id": 2,
      "class_name": "patches",
      "conf": 0.9216402173042297,
      "x1": 76.7123031616211,
      "y1": 249.6885986328125,
      "x2": 194.31396484375,
      "y2": 540.852294921875
    },
    {
      "image_name": "test_60.jpg",
      "class_id": 0,
      "class_name": "Rust",
      "conf": 0.8643104434013367,
      "x1": 216.1083221435547,
      "y1": 22.36402130126953,
      "x2": 311.75152587890625,
      "y2": 170.7500457763672
    },
    {
      "image_name": "test_63.jpg",
      "class_id": 0,
      "class_name": "Rust",
      "conf": 0.756717324256897,
      "x1": 240.36215209960938,
      "y1": 224.58290100097656,
      "x2": 390.16229248046875,
      "y2": 424.40576171875
    },
    {
      "image_name": "test_64.jpg",
      "class_id": 0,
      "class_name": "Rust",
      "conf": 0.5228112936019897,
      "x1": 225.45199584960938,
      "y1": 222.9798583984375,
      "x2": 639.0,
      "y2": 409.3019714355469
    },
    {
      "image_name": "test_65.jpg",
      "class_id": 0,
      "class_name": "Rust",
      "conf": 0.5143622159957886,
      "x1": 25.858612060546875,
      "y1": 216.90032958984375,
      "x2": 399.20330810546875,
      "y2": 420.3047790527344
    },
    {
      "image_name": "test_66.jpg",
      "class_id": 4,
      "class_name": "Pitting",
      "conf": 0.722527027130127,
      "x1": 272.73284912109375,
      "y1": 274.2564392089844,
      "x2": 377.0411376953125,
      "y2": 382.2620849609375
    },
    {
      "image_name": "test_7.jpg",
      "class_id": 4,
      "class_name": "Pitting",
      "conf": 0.8552476763725281,
      "x1": 215.86508178710938,
      "y1": 238.30545043945312,
      "x2": 430.4942626953125,
      "y2": 400.17041015625
    },
    {
      "image_name": "test_70.jpg",
      "class_id": 0,
      "class_name": "Rust",
      "conf": 0.7629542946815491,
      "x1": 242.6735076904297,
      "y1": 213.95693969726562,
      "x2": 575.5908203125,
      "y2": 424.3705749511719
    },
    {
      "image_name": "test_71.jpg",
      "class_id": 0,
      "class_name": "Rust",
      "conf": 0.7592254281044006,
      "x1": 232.88540649414062,
      "y1": 218.80804443359375,
      "x2": 639.0,
      "y2": 411.6653747558594
    },
    {
      "image_name": "test_72.jpg",
      "class_id": 0,
      "class_name": "Rust",
      "conf": 0.5176776051521301,
      "x1": 555.89404296875,
      "y1": 248.06031799316406,
      "x2": 639.0,
      "y2": 409.8385314941406
    },
    {
      "image_name": "test_73.jpg",
      "class_id": 4,
      "class_name": "Pitting",
      "conf": 0.4245312809944153,
      "x1": 287.3621520996094,
      "y1": 265.872802734375,
      "x2": 353.8055419921875,
      "y2": 354.6264343261719
    },
    {
      "image_name": "test_75.jpg",
      "class_id": 0,
      "class_name": "Rust",
      "conf": 0.9396923184394836,
      "x1": 263.42596435546875,
      "y1": 242.46434020996094,
      "x2": 383.69793701171875,
      "y2": 402.36566162109375
    },
    {
      "image_name": "test_75.jpg",
      "class_id": 0,
      "class_name": "Rust",
      "conf": 0.9223425984382629,
      "x1": 0.5416107177734375,
      "y1": 250.14378356933594,
      "x2": 172.503173828125,
      "y2": 500.8149719238281
    },
    {
      "image_name": "test_76.jpg",
      "class_id": 0,
      "class_name": "Rust",
      "conf": 0.9265698790550232,
      "x1": 246.98374938964844,
      "y1": 240.25244140625,
      "x2": 396.80133056640625,
      "y2": 403.60736083984375
    },
    {
      "image_name": "test_76.jpg",
      "class_id": 0,
      "class_name": "Rust",
      "conf": 0.9261703491210938,
      "x1": 452.52947998046875,
      "y1": 234.45997619628906,
      "x2": 531.9035034179688,
      "y2": 336.13641357421875
    },
    {
      "image_name": "test_77.jpg",
      "class_id": 0,
      "class_name": "Rust",
      "conf": 0.9213575720787048,
      "x1": 264.9298400878906,
      "y1": 240.6983642578125,
      "x2": 380.19091796875,
      "y2": 402.90399169921875
    },
    {
      "image_name": "test_78.jpg",
      "class_id": 0,
      "class_name": "Rust",
      "conf": 0.925499677658081,
      "x1": 240.12660217285156,
      "y1": 330.1413879394531,
      "x2": 397.9507141113281,
      "y2": 452.5323181152344
    },
    {
      "image_name": "test_79.jpg",
      "class_id": 0,
      "class_name": "Rust",
      "conf": 0.9383503198623657,
      "x1": 263.75152587890625,
      "y1": 242.1787109375,
      "x2": 382.9104919433594,
      "y2": 401.3247375488281
    },
    {
      "image_name": "test_79.jpg",
      "class_id": 0,
      "class_name": "Rust",
      "conf": 0.9174507260322571,
      "x1": 0.40111541748046875,
      "y1": 249.99295043945312,
      "x2": 172.77410888671875,
      "y2": 501.3240661621094
    },
    {
      "image_name": "test_8.jpg",
      "class_id": 2,
      "class_name": "patches",
      "conf": 0.9314625263214111,
      "x1": 365.1171875,
      "y1": 226.5784454345703,
      "x2": 521.125732421875,
      "y2": 585.42919921875
    },
    {
      "image_name": "test_8.jpg",
      "class_id": 2,
      "class_name": "patches",
      "conf": 0.8472108244895935,
      "x1": 589.865966796875,
      "y1": 116.4078598022461,
      "x2": 639.0,
      "y2": 250.66506958007812
    },
    {
      "image_name": "test_80.jpg",
      "class_id": 0,
      "class_name": "Rust",
      "conf": 0.9287972450256348,
      "x1": 247.8759307861328,
      "y1": 242.3431396484375,
      "x2": 396.1444396972656,
      "y2": 403.6470947265625
    },
    {
      "image_name": "test_80.jpg",
      "class_id": 0,
      "class_name": "Rust",
      "conf": 0.9242786765098572,
      "x1": 452.5891418457031,
      "y1": 233.98385620117188,
      "x2": 531.4278564453125,
      "y2": 335.074951171875
    },
    {
      "image_name": "test_81.jpg",
      "class_id": 0,
      "class_name": "Rust",
      "conf": 0.9282788634300232,
      "x1": 265.58148193359375,
      "y1": 240.19387817382812,
      "x2": 381.2678527832031,
      "y2": 400.9054260253906
    },
    {
      "image_name": "test_82.jpg",
      "class_id": 0,
      "class_name": "Rust",
      "conf": 0.9273632764816284,
      "x1": 240.69517517089844,
      "y1": 261.82208251953125,
      "x2": 396.69793701171875,
      "y2": 380.8409729003906
    },
    {
      "image_name": "test_83.jpg",
      "class_id": 0,
      "class_name": "Rust",
      "conf": 0.9370958209037781,
      "x1": 259.3059387207031,
      "y1": 242.40289306640625,
      "x2": 378.2796936035156,
      "y2": 401.61090087890625
    },
    {
      "image_name": "test_83.jpg",
      "class_id": 0,
      "class_name": "Rust",
      "conf": 0.9152045845985413,
      "x1": 0.32390594482421875,
      "y1": 248.9197235107422,
      "x2": 170.23126220703125,
      "y2": 501.1178894042969
    },
    {
      "image_name": "test_84.jpg",
      "class_id": 0,
      "class_name": "Rust",
      "conf": 0.9284088015556335,
      "x1": 247.34527587890625,
      "y1": 240.57008361816406,
      "x2": 396.25848388671875,
      "y2": 402.91546630859375
    },
    {
      "image_name": "test_84.jpg",
      "class_id": 0,
      "class_name": "Rust",
      "conf": 0.9269675612449646,
      "x1": 452.446044921875,
      "y1": 234.67694091796875,
      "x2": 531.6305541992188,
      "y2": 337.1549987792969
    },
    {
      "image_name": "test_85.jpg",
      "class_id": 0,
      "class_name": "Rust",
      "conf": 0.8987665772438049,
      "x1": 464.05535888671875,
      "y1": 552.5179443359375,
      "x2": 622.1707763671875,
      "y2": 639.0
    },
    {
      "image_name": "test_85.jpg",
      "class_id": 0,
      "class_name": "Rust",
      "conf": 0.7102264761924744,
      "x1": 0.41451454162597656,
      "y1": 238.89703369140625,
      "x2": 28.41767692565918,
      "y2": 396.40533447265625
    },
    {
      "image_name": "test_86.jpg",
      "class_id": 0,
      "class_name": "Rust",
      "conf": 0.9276259541511536,
      "x1": 240.06378173828125,
      "y1": 330.1954650878906,
      "x2": 397.3627624511719,
      "y2": 452.2424011230469
    },
    {
      "image_name": "test_87.jpg",
      "class_id": 0,
      "class_name": "Rust",
      "conf": 0.9375547766685486,
      "x1": 258.6668701171875,
      "y1": 242.4571533203125,
      "x2": 377.427001953125,
      "y2": 399.3704833984375
    },
    {
      "image_name": "test_87.jpg",
      "class_id": 0,
      "class_name": "Rust",
      "conf": 0.9147487282752991,
      "x1": 0.3209381103515625,
      "y1": 250.10821533203125,
      "x2": 170.92495727539062,
      "y2": 500.2558898925781
    },
    {
      "image_name": "test_88.jpg",
      "class_id": 0,
      "class_name": "Rust",
      "conf": 0.9308364987373352,
      "x1": 248.2027587890625,
      "y1": 241.83790588378906,
      "x2": 397.2425231933594,
      "y2": 403.36077880859375
    },
    {
      "image_name": "test_88.jpg",
      "class_id": 0,
      "class_name": "Rust",
      "conf": 0.9242786765098572,
      "x1": 452.6711120605469,
      "y1": 234.1241455078125,
      "x2": 531.3350830078125,
      "y2": 336.0065002441406
    },
    {
      "image_name": "test_89.jpg",
      "class_id": 0,
      "class_name": "Rust",
      "conf": 0.907312273979187,
      "x1": 466.38763427734375,
      "y1": 553.1175537109375,
      "x2": 618.6228637695312,
      "y2": 639.0
    },
    {
      "image_name": "test_89.jpg",
      "class_id": 0,
      "class_name": "Rust",
      "conf": 0.5488548874855042,
      "x1": 0.46407318115234375,
      "y1": 241.19650268554688,
      "x2": 28.270565032958984,
      "y2": 394.9068603515625
    },
    {
      "image_name": "test_9.jpg",
      "class_id": 2,
      "class_name": "patches",
      "conf": 0.9314625263214111,
      "x1": 365.1171875,
      "y1": 226.5784454345703,
      "x2": 521.125732421875,
      "y2": 585.42919921875
    },
    {
      "image_name": "test_9.jpg",
      "class_id": 2,
      "class_name": "patches",
      "conf": 0.8472108244895935,
      "x1": 589.865966796875,
      "y1": 116.4078598022461,
      "x2": 639.0,
      "y2": 250.66506958007812
    },
    {
      "image_name": "test_90.jpg",
      "class_id": 0,
      "class_name": "Rust",
      "conf": 0.9313377141952515,
      "x1": 241.285888671875,
      "y1": 262.0789489746094,
      "x2": 396.2344055175781,
      "y2": 380.4194030761719
    },
    {
      "image_name": "test_94.jpg",
      "class_id": 0,
      "class_name": "Rust",
      "conf": 0.3591393530368805,
      "x1": 280.93231201171875,
      "y1": 0.26500701904296875,
      "x2": 409.4886474609375,
      "y2": 137.31298828125
    },
    {
      "image_name": "test_96.jpg",
      "class_id": 0,
      "class_name": "Rust",
      "conf": 0.6153768301010132,
      "x1": 280.38818359375,
      "y1": 136.17642211914062,
      "x2": 376.8670959472656,
      "y2": 426.56634521484375
    }
  ]
}